Workbook

Sheet Weights
A1: Parameter | B1: Value
A2: w_base_score | B2: 1
A3: w_facilities | B3: 0.45
A4: w_confidence | B4: 1
A5: max_facilities_cap | B5: 500
A7: Notes
A8: Priority_Score = (Score*w_base_score) + (MIN(Facilities_Est,cap) * w_facilities * (Confidence/100) * w_confidence)

Sheet Research Queue
A1: Company | B1: Tier | C1: Score | D1: Facilities_Est | E1: Confidence | F1: Evidence_URL_1 | G1: Method | H1: Notes | I1: Assigned_To | J1: Status
A2: Ajinomoto Foods North America, Inc. | B2: Tier 3 | C2: 55 | D2: =IFERROR(INDEX('Company Hitlist'!$Q:$Q,MATCH($A2,'Company Hitlist'!$A:$A,0)),) | E2: =IFERROR(INDEX('Company Hitlist'!$W:$W,MATCH($A2,'Company Hitlist'!$A:$A,0)),) | F2: =IFERROR(INDEX('Company Hitlist'!$T:$T,MATCH($A2,'Company Hitlist'!$A:$A,0)),) | G2: =IFERROR(INDEX('Company Hitlist'!$V:$V,MATCH($A2,'Company Hitlist'!$A:$A,0)),) | J2: todo
A3: CHS, Inc. | B3: Tier 3 | C3: 52 | D3: =IFERROR(INDEX('Company Hitlist'!$Q:$Q,MATCH($A3,'Company Hitlist'!$A:$A,0)),) | E3: =IFERROR(INDEX('Company Hitlist'!$W:$W,MATCH($A3,'Company Hitlist'!$A:$A,0)),) | F3: =IFERROR(INDEX('Company Hitlist'!$T:$T,MATCH($A3,'Company Hitlist'!$A:$A,0)),) | G3: =IFERROR(INDEX('Company Hitlist'!$V:$V,MATCH($A3,'Company Hitlist'!$A:$A,0)),) | J3: todo
A4: APL Logistics | B4: Tier 3 | C4: 51 | D4: =IFERROR(INDEX('Company Hitlist'!$Q:$Q,MATCH($A4,'Company Hitlist'!$A:$A,0)),) | E4: =IFERROR(INDEX('Company Hitlist'!$W:$W,MATCH($A4,'Company Hitlist'!$A:$A,0)),) | F4: =IFERROR(INDEX('Company Hitlist'!$T:$T,MATCH($A4,'Company Hitlist'!$A:$A,0)),) | G4: =IFERROR(INDEX('Company Hitlist'!$V:$V,MATCH($A4,'Company Hitlist'!$A:$A,0)),) | J4: todo
A5: BarkBox | B5: Tier 3 | C5: 50 | D5: =IFERROR(INDEX('Company Hitlist'!$Q:$Q,MATCH($A5,'Company Hitlist'!$A:$A,0)),) | E5: =IFERROR(INDEX('Company Hitlist'!$W:$W,MATCH($A5,'Company Hitlist'!$A:$A,0)),) | F5: =IFERROR(INDEX('Company Hitlist'!$T:$T,MATCH($A5,'Company Hitlist'!$A:$A,0)),) | G5: =IFERROR(INDEX('Company Hitlist'!$V:$V,MATCH($A5,'Company Hitlist'!$A:$A,0)),) | J5: todo
A6: Logitech | B6: Tier 3 | C6: 50 | D6: =IFERROR(INDEX('Company Hitlist'!$Q:$Q,MATCH($A6,'Company Hitlist'!$A:$A,0)),) | E6: =IFERROR(INDEX('Company Hitlist'!$W:$W,MATCH($A6,'Company Hitlist'!$A:$A,0)),) | F6: =IFERROR(INDEX('Company Hitlist'!$T:$T,MATCH($A6,'Company Hitlist'!$A:$A,0)),) | G6: =IFERROR(INDEX('Company Hitlist'!$V:$V,MATCH($A6,'Company Hitlist'!$A:$A,0)),) | J6: todo
A7: Stitch Fix | B7: Tier 3 | C7: 50 | D7: =IFERROR(INDEX('Company Hitlist'!$Q:$Q,MATCH($A7,'Company Hitlist'!$A:$A,0)),) | E7: =IFERROR(INDEX('Company Hitlist'!$W:$W,MATCH($A7,'Company Hitlist'!$A:$A,0)),) | F7: =IFERROR(INDEX('Company Hitlist'!$T:$T,MATCH($A7,'Company Hitlist'!$A:$A,0)),) | G7: =IFERROR(INDEX('Company Hitlist'!$V:$V,MATCH($A7,'Company Hitlist'!$A:$A,0)),) | J7: todo
A8: AEO | B8: Tier 3 | C8: 48 | D8: =IFERROR(INDEX('Company Hitlist'!$Q:$Q,MATCH($A8,'Company Hitlist'!$A:$A,0)),) | E8: =IFERROR(INDEX('Company Hitlist'!$W:$W,MATCH($A8,'Company Hitlist'!$A:$A,0)),) | F8: =IFERROR(INDEX('Company Hitlist'!$T:$T,MATCH($A8,'Company Hitlist'!$A:$A,0)),) | G8: =IFERROR(INDEX('Company Hitlist'!$V:$V,MATCH($A8,'Company Hitlist'!$A:$A,0)),) | J8: todo
A9: Johnson & Johnson | B9: Tier 3 | C9: 46 | D9: =IFERROR(INDEX('Company Hitlist'!$Q:$Q,MATCH($A9,'Company Hitlist'!$A:$A,0)),) | E9: =IFERROR(INDEX('Company Hitlist'!$W:$W,MATCH($A9,'Company Hitlist'!$A:$A,0)),) | F9: =IFERROR(INDEX('Company Hitlist'!$T:$T,MATCH($A9,'Company Hitlist'!$A:$A,0)),) | G9: =IFERROR(INDEX('Company Hitlist'!$V:$V,MATCH($A9,'Company Hitlist'!$A:$A,0)),) | J9: todo
A10: Kenco | B10: Tier 3 | C10: 46 | D10: =IFERROR(INDEX('Company Hitlist'!$Q:$Q,MATCH($A10,'Company Hitlist'!$A:$A,0)),) | E10: =IFERROR(INDEX('Company Hitlist'!$W:$W,MATCH($A10,'Company Hitlist'!$A:$A,0)),) | F10: =IFERROR(INDEX('Company Hitlist'!$T:$T,MATCH($A10,'Company Hitlist'!$A:$A,0)),) | G10: =IFERROR(INDEX('Company Hitlist'!$V:$V,MATCH($A10,'Company Hitlist'!$A:$A,0)),) | J10: todo
A11: Caraway | B11: Tier 3 | C11: 45 | D11: =IFERROR(INDEX('Company Hitlist'!$Q:$Q,MATCH($A11,'Company Hitlist'!$A:$A,0)),) | E11: =IFERROR(INDEX('Company Hitlist'!$W:$W,MATCH($A11,'Company Hitlist'!$A:$A,0)),) | F11: =IFERROR(INDEX('Company Hitlist'!$T:$T,MATCH($A11,'Company Hitlist'!$A:$A,0)),) | G11: =IFERROR(INDEX('Company Hitlist'!$V:$V,MATCH($A11,'Company Hitlist'!$A:$A,0)),) | J11: todo
A12: Aterian | B12: Tier 3 | C12: 45 | D12: =IFERROR(INDEX('Company Hitlist'!$Q:$Q,MATCH($A12,'Company Hitlist'!$A:$A,0)),) | E12: =IFERROR(INDEX('Company Hitlist'!$W:$W,MATCH($A12,'Company Hitlist'!$A:$A,0)),) | F12: =IFERROR(INDEX('Company Hitlist'!$T:$T,MATCH($A12,'Company Hitlist'!$A:$A,0)),) | G12: =IFERROR(INDEX('Company Hitlist'!$V:$V,MATCH($A12,'Company Hitlist'!$A:$A,0)),) | J12: todo
A13: Globe Electric | B13: Tier 3 | C13: 45 | D13: =IFERROR(INDEX('Company Hitlist'!$Q:$Q,MATCH($A13,'Company Hitlist'!$A:$A,0)),) | E13: =IFERROR(INDEX('Company Hitlist'!$W:$W,MATCH($A13,'Company Hitlist'!$A:$A,0)),) | F13: =IFERROR(INDEX('Company Hitlist'!$T:$T,MATCH($A13,'Company Hitlist'!$A:$A,0)),) | G13: =IFERROR(INDEX('Company Hitlist'!$V:$V,MATCH($A13,'Company Hitlist'!$A:$A,0)),) | J13: todo
... A82: Global Industrial Company | B82: Tier 1 | C82: 82 | D82: =IFERROR(INDEX('Company Hitlist'!$Q:$Q,MATCH($A82,'Company Hitlist'!$A:$A,0)),) | E82: =IFERROR(INDEX('Company Hitlist'!$W:$W,MATCH($A82,'Company Hitlist'!$A:$A,0)),) | F82: =IFERROR(INDEX('Company Hitlist'!$T:$T,MATCH($A82,'Company Hitlist'!$A:$A,0)),) | G82: =IFERROR(INDEX('Company Hitlist'!$V:$V,MATCH($A82,'Company Hitlist'!$A:$A,0)),) | J82: todo

Sheet Company Hitlist
A1: Company | B1: attendees | C1: exec_ops_count | D1: ops_count | E1: proc_count | F1: sales_count | G1: tech_count | H1: max_revenue | I1: non_ops | J1: ops_share | K1: vendor_penalty | L1: mega_boost | M1: Score | N1: Tier | O1: Recommended Targets | P1: TopTitles | Q1: Facilities_Est | R1: Yards_Est | S1: Facility_Type | T1: Evidence_URL_1 | U1: Evidence_URL_2 | V1: Method | W1: Confidence | X1: Last_Verified | Y1: Enrichment_Status | Z1: Priority_Score | AA1: Priority_Rank
A2: Mars | B2: 9 | C2: 0 | D2: 6 | E2: 1 | F2: 0 | G2: 1 | I2: 1 | J2: 0.66666667 | K2: 0 | L2: 0 | M2: 35 | N2: Tier 4 | O2: Michael Ventura — Manager, Strategic Sourcing - Transportation; Mike Shaverin — Global Supply Chain Director; Meghan Charboneau — Director of Transportation; Isaiah Viera — Global Warehouse Operations Manager; Josh Mullis — Global Supply Chain Director - Mars Retail | P2: Manager, Strategic Sourcing - Transportation | Director of Transportation | SVP of Global Analytics, Digital & Data | Y2: todo | Z2: =(M2*Weights!$B$2) + (MIN(Q2,Weights!$B$5)*Weights!$B$3*(W2/100)*Weights!$B$4) | AA2: =IF(Z2= ,,RANK.EQ({pri_col_letter}{r},{pri_range},0))
A3: SEKO Logistics | B3: 7 | C3: 0 | D3: 2 | E3: 0 | F3: 0 | G3: 1 | H3: 2000000000 | I3: 1 | J3: 0.28571429 | K3: 0 | L3: 0 | M3: 35 | N3: Tier 4 | O3: Caleb Alvis — Commercial Operations Manager; Dina Stillo — Director of Program Development, Supply Chain & Logistics; Brian Bourke — Chief Commerical Officer; Brock McMorris — Vice President, Global Strategic Clients; Jamie Andrade — SVP, Product Management | P3: Chief Commerical Officer | Vice President, Global Strategic Clients | SVP, Product Management | Y3: todo | Z3: =(M3*Weights!$B$2) + (MIN(Q3,Weights!$B$5)*Weights!$B$3*(W3/100)*Weights!$B$4) | AA3: =IF(Z3= ,,RANK.EQ({pri_col_letter}{r},{pri_range},0))
A4: Wayfair | B4: 2 | C4: 0 | D4: 1 | E4: 1 | F4: 0 | G4: 0 | I4: 0 | J4: 0.5 | K4: 0 | L4: 25 | M4: 33 | N4: Tier 4 | O4: Kenneth Sine — Head of Global Procurement; Chayan Ray — Senior Manager, Global Transportation Systems | P4: Head of Global Procurement | Senior Manager, Global Transportation Systems | Y4: todo | Z4: =(M4*Weights!$B$2) + (MIN(Q4,Weights!$B$5)*Weights!$B$3*(W4/100)*Weights!$B$4) | AA4: =IF(Z4= ,,RANK.EQ({pri_col_letter}{r},{pri_range},0))
A5: Light & Wonder | B5: 12 | C5: 0 | D5: 2 | E5: 6 | F5: 0 | G5: 0 | I5: 0 | J5: 0.16666667 | K5: 0 | L5: 0 | M5: 32 | N5: Tier 4 | O5: Jennifer Krueger — Vice President, Planning & Purchasing; Eric Eileraas — Sr Director Logistics; Rachael Leggett — Sr Director, Supply Chain Strategy & Demand Planning; Deb Withers — Sr Manager, Purchasing; Eric Sill — Director, Supply Planning & Purchasing | P5: Vice President, Planning & Purchasing | COO | Vice President, Field Services | Y5: todo | Z5: =(M5*Weights!$B$2) + (MIN(Q5,Weights!$B$5)*Weights!$B$3*(W5/100)*Weights!$B$4) | AA5: =IF(Z5= ,,RANK.EQ({pri_col_letter}{r},{pri_range},0))
A6: KBX | B6: 7 | C6: 1 | D6: 2 | E6: 1 | F6: 0 | G6: 0 | I6: 0 | J6: 0.28571429 | K6: 0 | L6: 0 | M6: 32 | N6: Tier 4 | O6: Jamie Hess — VP, Global Transportation Procurement; David Bennett — Sr. Managing Director, International Logistics; Richard Swan — KBX President; Ryan Winter — CFO; Scott Reed — CIO | P6: VP, Global Transportation Procurement | Sr. Managing Director, International Logistics | KBX President | Y6: todo | Z6: =(M6*Weights!$B$2) + (MIN(Q6,Weights!$B$5)*Weights!$B$3*(W6/100)*Weights!$B$4) | AA6: =IF(Z6= ,,RANK.EQ({pri_col_letter}{r},{pri_range},0))
A7: iFIT | B7: 5 | C7: 1 | D7: 3 | E7: 0 | F7: 0 | G7: 0 | I7: 0 | J7: 0.6 | K7: 0 | L7: 0 | M7: 32 | N7: Tier 4 | O7: Robert Critchley — VP, Transportation & Warehousing; Mike Buttars — Reverse Logistics; Ron Stimson — Director of Reverse logistics; Paul Bozich — Director of Home Delivery; Chelsey Porter — Carrier Relations Manager | P7: VP, Transportation & Warehousing | Reverse Logistics | Director of Reverse logistics | Y7: todo | Z7: =(M7*Weights!$B$2) + (MIN(Q7,Weights!$B$5)*Weights!$B$3*(W7/100)*Weights!$B$4) | AA7: =IF(Z7= ,,RANK.EQ({pri_col_letter}{r},{pri_range},0))
A8: Nike | B8: 3 | C8: 0 | D8: 1 | E8: 0 | F8: 0 | G8: 0 | I8: 0 | J8: 0.33333333 | K8: 0 | L8: 25 | M8: 32 | N8: Tier 4 | O8: Vishal Arya — Sr Director of Transportation and Trade; Lukesh Singla — Material Planning Leader; Brian Gooch — Sr. Manager, Capacity Performance and Planning | P8: Sr Director of Transportation and Trade | Material Planning Leader | Sr. Manager, Capacity Performance and Planning | Y8: todo | Z8: =(M8*Weights!$B$2) + (MIN(Q8,Weights!$B$5)*Weights!$B$3*(W8/100)*Weights!$B$4) | AA8: =IF(Z8= ,,RANK.EQ({pri_col_letter}{r},{pri_range},0))
A9: Aristocrat Gaming | B9: 4 | C9: 1 | D9: 3 | E9: 0 | F9: 0 | G9: 1 | I9: 1 | J9: 0.75 | K9: 0 | L9: 0 | M9: 31 | N9: Tier 4 | O9: Mihir Wagh — SVP, GSC Manufacturing & Logistics; Caleb Lawrence — Senior Analyst Global Logistics; Erin Turner — Sr. Manager, Global Logistics; Amit Bakuli — VP-Manufacturing Engineering | P9: SVP, GSC Manufacturing & Logistics | VP-Manufacturing Engineering | Senior Analyst Global Logistics | Y9: todo | Z9: =(M9*Weights!$B$2) + (MIN(Q9,Weights!$B$5)*Weights!$B$3*(W9/100)*Weights!$B$4) | AA9: =IF(Z9= ,,RANK.EQ({pri_col_letter}{r},{pri_range},0))
A10: Peloton Interactive | B10: 4 | C10: 1 | D10: 2 | E10: 2 | F10: 0 | G10: 0 | I10: 0 | J10: 0.5 | K10: 0 | L10: 0 | M10: 31 | N10: Tier 4 | O10: Andy Rendich — Chief Supply Chain Officer; David Beyar — Sr. Manager, Transportation; Angad Gadhok — Senior Manager, Procurement; Bharat Nair — Category Manager, Procurement | P10: Chief Supply Chain Officer | Sr. Manager, Transportation | Senior Manager, Procurement | Y10: todo | Z10: =(M10*Weights!$B$2) + (MIN(Q10,Weights!$B$5)*Weights!$B$3*(W10/100)*Weights!$B$4) | AA10: =IF(Z10= ,,RANK.EQ({pri_col_letter}{r},{pri_range},0))
A11: Philips | B11: 4 | C11: 1 | D11: 3 | E11: 0 | F11: 0 | G11: 0 | I11: 0 | J11: 0.75 | K11: 0 | L11: 0 | M11: 31 | N11: Tier 4 | O11: Birger Buesching — Head of Supply Chain North America, Personal Health; Ryan Ganger — Transportation Leader North America; Marc Koumoundouros — Supply Chain Leader Canada; Laura de Chiara — Director Transformation and Integration | P11: Head of Supply Chain North America, Personal Health | Transportation Leader North America | Supply Chain Leader Canada | Y11: todo | Z11: =(M11*Weights!$B$2) + (MIN(Q11,Weights!$B$5)*Weights!$B$3*(W11/100)*Weights!$B$4) | AA11: =IF(Z11= ,,RANK.EQ({pri_col_letter}{r},{pri_range},0))
A12: Tyson Foods | B12: 2 | C12: 0 | D12: 1 | E12: 0 | F12: 0 | G12: 0 | I12: 0 | J12: 0.5 | K12: 0 | L12: 25 | M12: 31 | N12: Tier 4 | O12: Chris Plant — Director of Transportation; Kevin Corrigan — Associate Director, Business Process & Systems | P12: Director of Transportation | Associate Director, Business Process & Systems | Y12: todo | Z12: =(M12*Weights!$B$2) + (MIN(Q12,Weights!$B$5)*Weights!$B$3*(W12/100)*Weights!$B$4) | AA12: =IF(Z12= ,,RANK.EQ({pri_col_letter}{r},{pri_range},0))
A13: AT&T | B13: 6 | C13: 0 | D13: 6 | E13: 0 | F13: 0 | G13: 0 | I13: 0 | J13: 1 | K13: 0 | L13: 0 | M13: 30 | N13: Tier 4 | O13: Ellen Valencia — AVP Planning and Logistics; Jawad Masood — Director Planning and Logistics; Kent McCormick — Director Supply Planning/Logistics; Kyle Meyer — Director Planning and Logistics; Meg Birchfiled — Director Planning & Logistics | P13: AVP Planning and Logistics | Director Planning and Logistics | Director Supply Planning/Logistics | Y13: todo | Z13: =(M13*Weights!$B$2) + (MIN(Q13,Weights!$B$5)*Weights!$B$3*(W13/100)*Weights!$B$4) | AA13: =IF(Z13= ,,RANK.EQ({pri_col_letter}{r},{pri_range},0))
A14: Google Cloud | B14: 5 | C14: 1 | D14: 4 | E14: 0 | F14: 3 | G14: 2 | I14: 5 | J14: 0.8 | K14: 0 | L14: 0 | M14: 30 | N14: Tier 4 | O14: Mike Mandeville — Head of Customer Engineering, Logistics; Shayna Zweiback — Regional Marketing Lead, South and Logistics; Peter Blum — Director, US Logistics Sales; Ashwin Sridhar — Global Solutions Lead, Industry AI; Yewande Badewole — Global GTM Practice Architect - Logistics & Supply Chain | P14: Head of Customer Engineering, Logistics | Global Solutions Lead, Industry AI | Regional Marketing Lead, South and Logistics | Y14: todo | Z14: =(M14*Weights!$B$2) + (MIN(Q14,Weights!$B$5)*Weights!$B$3*(W14/100)*Weights!$B$4) | AA14: =IF(Z14= ,,RANK.EQ({pri_col_letter}{r},{pri_range},0))
A15: Dermalogica | B15: 3 | C15: 1 | D15: 3 | E15: 0 | F15: 0 | G15: 1 | I15: 1 | J15: 1 | K15: 0 | L15: 0 | M15: 30 | N15: Tier 4 | O15: John McGuinn — VP Operations; Jason Brown — Director Logistics & Warehousing; Ashley Deleonardis — Supply Chain Process Architect | P15: VP Operations | Director Logistics & Warehousing | Supply Chain Process Architect | Y15: todo | Z15: =(M15*Weights!$B$2) + (MIN(Q15,Weights!$B$5)*Weights!$B$3*(W15/100)*Weights!$B$4) | AA15: =IF(Z15= ,,RANK.EQ({pri_col_letter}{r},{pri_range},0))
... A22: Kuehne + Nagel | B22: 4 | C22: 0 | D22: 0 | E22: 0 | F22: 0 | G22: 0 | I22: 0 | J22: 0 | K22: 0 | L22: 25 | M22: 29 | N22: Tier 4 | O22: David Cornett — VP Healthcare Americas; Donald Potter — VP Consumer Americas; Liam Harris — VP Technology Americas; Ryan Pope — Director, Key Accounts Development | P22: VP Healthcare Americas | VP Consumer Americas | VP Technology Americas | Y22: todo | Z22: =(M22*Weights!$B$2) + (MIN(Q22,Weights!$B$5)*Weights!$B$3*(W22/100)*Weights!$B$4) | AA22: =IF(Z22= ,,RANK.EQ({pri_col_letter}{r},{pri_range},0))
A23: Zero Down Supply Chain Solutions | B23: 5 | C23: 1 | D23: 1 | E23: 0 | F23: 1 | G23: 0 | H23: 54436000 | I23: 1 | J23: 0.2 | K23: 0 | L23: 0 | M23: 28 | N23: Tier 4 | O23: Saxon McBride — Vice President of Operations; Brad McBride — CEO & Founder; Reinaldo Marin — COO; James Reilly II — Director of Client Acquisition; Rebecca McBride — Director of Business Development | P23: Vice President of Operations | CEO & Founder | COO | Y23: todo | Z23: =(M23*Weights!$B$2) + (MIN(Q23,Weights!$B$5)*Weights!$B$3*(W23/100)*Weights!$B$4) | AA23: =IF(Z23= ,,RANK.EQ({pri_col_letter}{r},{pri_range},0))
A24: Hunter Douglas | B24: 3 | C24: 1 | D24: 2 | E24: 1 | F24: 0 | G24: 0 | I24: 0 | J24: 0.66666667 | K24: 0 | L24: 0 | M24: 28 | N24: Tier 4 | O24: Nikki Soss — Head of Enterprise Logistics & Distribution; Andrew Curtin — Customer Delivery Logistics Leader; Christian Schaffner — Global Category Director - Freight & Packaging Procurement | P24: Head of Enterprise Logistics & Distribution | Customer Delivery Logistics Leader | Global Category Director - Freight & Packaging Procurement | Y24: todo | Z24: =(M24*Weights!$B$2) + (MIN(Q24,Weights!$B$5)*Weights!$B$3*(W24/100)*Weights!$B$4) | AA24: =IF(Z24= ,,RANK.EQ({pri_col_letter}{r},{pri_range},0))
A25: Revolve | B25: 3 | C25: 1 | D25: 2 | E25: 1 | F25: 0 | G25: 0 | I25: 0 | J25: 0.66666667 | K25: 0 | L25: 0 | M25: 28 | N25: Tier 4 | O25: Heather Burke — SVP Logistics & Customer Experience; Tony (King) Chow — Sr Director of Operations; Blanka Holubcova — Sr Purchasing Manager | P25: SVP Logistics & Customer Experience | Sr Director of Operations | Sr Purchasing Manager | Y25: todo | Z25: =(M25*Weights!$B$2) + (MIN(Q25,Weights!$B$5)*Weights!$B$3*(W25/100)*Weights!$B$4) | AA25: =IF(Z25= ,,RANK.EQ({pri_col_letter}{r},{pri_range},0))
A26: SAMSUNG SDS | B26: 10 | C26: 1 | D26: 1 | E26: 0 | F26: 1 | G26: 0 | I26: 1 | J26: 0.1 | K26: 0 | L26: 0 | M26: 27 | N26: Tier 4 | O26: Wilco Koers — Vice President Contract Logistics; Seungpyo Hong — Head of Business Team; Sungju Kim — Vice President; Jihyun Lim — Vice President; Sunggon Kim — Vice President | P26: Vice President Contract Logistics | Head of Business Team | Vice President | Y26: todo | Z26: =(M26*Weights!$B$2) + (MIN(Q26,Weights!$B$5)*Weights!$B$3*(W26/100)*Weights!$B$4) | AA26: =IF(Z26= ,,RANK.EQ({pri_col_letter}{r},{pri_range},0))
A27: Backhaul Direct | B27: 4 | C27: 1 | D27: 2 | E27: 0 | F27: 0 | G27: 0 | I27: 0 | J27: 0.5 | K27: 0 | L27: 0 | M27: 27 | N27: Tier 4 | O27: Dylan Murphy — President & Chief Operations Officer; Dylan Mollo — Tech Operations Lead; Gregory Harris — Founder/CEO; Scott Mulholland — Senior Vice President | P27: President & Chief Operations Officer | Tech Operations Lead | Founder/CEO | Y27: todo | Z27: =(M27*Weights!$B$2) + (MIN(Q27,Weights!$B$5)*Weights!$B$3*(W27/100)*Weights!$B$4) | AA27: =IF(Z27= ,,RANK.EQ({pri_col_letter}{r},{pri_range},0))
A28: Fives Intralogistics Corp. | B28: 4 | C28: 1 | D28: 3 | E28: 0 | F28: 2 | G28: 0 | I28: 2 | J28: 0.75 | K28: 0 | L28: 0 | M28: 27 | N28: Tier 4 | O28: Phillip Agans — VP of Warehouse & Distribution Solutions; Mike Stearns — Director of Warehouse and Distribution; Brad Perry — Director of Warehouse & Distribution Sales; Allison Myers — Director of Marketing & Communications | P28: VP of Warehouse & Distribution Solutions | Director of Warehouse and Distribution | Director of Warehouse & Distribution Sales | Y28: todo | Z28: =(M28*Weights!$B$2) + (MIN(Q28,Weights!$B$5)*Weights!$B$3*(W28/100)*Weights!$B$4) | AA28: =IF(Z28= ,,RANK.EQ({pri_col_letter}{r},{pri_range},0))
A29: Owens Corning | B29: 2 | C29: 1 | D29: 2 | E29: 1 | F29: 0 | G29: 0 | I29: 0 | J29: 1 | K29: 0 | L29: 0 | M29: 27 | N29: Tier 4 | O29: Mohamed Saleh — Head of Logistics & Real Estate Sourcing & Supply Chain; Andrea Webster — Distribution and Warehouse Leader | P29: Head of Logistics & Real Estate Sourcing & Supply Chain | Distribution and Warehouse Leader | Y29: todo | Z29: =(M29*Weights!$B$2) + (MIN(Q29,Weights!$B$5)*Weights!$B$3*(W29/100)*Weights!$B$4) | AA29: =IF(Z29= ,,RANK.EQ({pri_col_letter}{r},{pri_range},0))
A30: Port of Miami | B30: 2 | C30: 0 | D30: 0 | E30: 0 | F30: 0 | G30: 0 | I30: 0 | J30: 0 | K30: 0 | L30: 25 | M30: 27 | N30: Tier 4 | O30: Chris Hudtwalcker — Head of Innovation; Gustavo Grande — Head of Innovation | P30: Head of Innovation | Y30: todo | Z30: =(M30*Weights!$B$2) + (MIN(Q30,Weights!$B$5)*Weights!$B$3*(W30/100)*Weights!$B$4) | AA30: =IF(Z30= ,,RANK.EQ({pri_col_letter}{r},{pri_range},0))
A31: FabFitFun | B31: 3 | C31: 1 | D31: 2 | E31: 0 | F31: 0 | G31: 1 | I31: 1 | J31: 0.66666667 | K31: 0 | L31: 0 | M31: 26 | N31: Tier 4 | O31: Julian VanErlach — SVP, Global Supply Chain & Customer Service; Nathan Goodrich — Sr. Director of Inventory and Logistics; Mark Gavin — Sr Director, Global IT | P31: SVP, Global Supply Chain & Customer Service | Sr. Director of Inventory and Logistics | Sr Director, Global IT | Y31: todo | Z31: =(M31*Weights!$B$2) + (MIN(Q31,Weights!$B$5)*Weights!$B$3*(W31/100)*Weights!$B$4) | AA31: =IF(Z31= ,,RANK.EQ({pri_col_letter}{r},{pri_range},0))
A32: NRS | B32: 3 | C32: 1 | D32: 2 | E32: 0 | F32: 0 | G32: 0 | I32: 0 | J32: 0.66666667 | K32: 0 | L32: 0 | M32: 26 | N32: Tier 4 | O32: Anthony Mayor — SVP Distribution; Christian Klein — Director of Operations Strategy; Jon Hoch — COO | P32: SVP Distribution | Director of Operations Strategy | COO | Y32: todo | Z32: =(M32*Weights!$B$2) + (MIN(Q32,Weights!$B$5)*Weights!$B$3*(W32/100)*Weights!$B$4) | AA32: =IF(Z32= ,,RANK.EQ({pri_col_letter}{r},{pri_range},0))
A33: Sobel-Westex | B33: 3 | C33: 1 | D33: 2 | E33: 0 | F33: 0 | G33: 0 | I33: 0 | J33: 0.66666667 | K33: 0 | L33: 0 | M33: 26 | N33: Tier 4 | O33: Alex Alarcon — Chief Administration & Operations Officer; Mike Ramirez — Project Logistics & Supply Chain Management; Luis Toro — Chief Information Officer | P33: Chief Administration & Operations Officer | Chief Information Officer | Project Logistics & Supply Chain Management | Y33: todo | Z33: =(M33*Weights!$B$2) + (MIN(Q33,Weights!$B$5)*Weights!$B$3*(W33/100)*Weights!$B$4) | AA33: =IF(Z33= ,,RANK.EQ({pri_col_letter}{r},{pri_range},0))
A34: APM Terminals - Los Angeles | B34: 1 | C34: 0 | D34: 0 | E34: 0 | F34: 0 | G34: 0 | I34: 0 | J34: 0 | K34: 0 | L34: 25 | M34: 26 | N34: Tier 4 | O34: Ashley Esparza — Key Client Director | P34: Key Client Director | Y34: todo | Z34: =(M34*Weights!$B$2) + (MIN(Q34,Weights!$B$5)*Weights!$B$3*(W34/100)*Weights!$B$4) | AA34: =IF(Z34= ,,RANK.EQ({pri_col_letter}{r},{pri_range},0))
A35: Amazon Robotics | B35: 1 | C35: 0 | D35: 0 | E35: 0 | F35: 0 | G35: 1 | I35: 1 | J35: 0 | K35: 0 | L35: 25 | M35: 26 | N35: Tier 4 | O35: Tej Sheth — Lead Solutions Design Engineer | P35: Lead Solutions Design Engineer | Y35: todo | Z35: =(M35*Weights!$B$2) + (MIN(Q35,Weights!$B$5)*Weights!$B$3*(W35/100)*Weights!$B$4) | AA35: =IF(Z35= ,,RANK.EQ({pri_col_letter}{r},{pri_range},0))
... A69: The Home Depot | B69: 11 | C69: 0 | D69: 1 | E69: 0 | F69: 2 | G69: 3 | I69: 5 | J69: 0.090909091 | K69: 12 | L69: 25 | M69: 24 | N69: Tier 4 | O69: Stuart Kilgus — DC Engineer, Innovation & Automation; Chris Smith — Vice President, Information Technology; Dan Jarvis — Vice President, Engineering & Automation; Jeff Andreski — Sr. Director, Information Technology; Joanna Kronberg — Director, Innovation & Automation | P69: Vice President, Information Technology | Vice President, Engineering & Automation | DC Engineer, Innovation & Automation | Y69: todo | Z69: =(M69*Weights!$B$2) + (MIN(Q69,Weights!$B$5)*Weights!$B$3*(W69/100)*Weights!$B$4) | AA69: =IF(Z69= ,,RANK.EQ({pri_col_letter}{r},{pri_range},0))
A70: FlavorCloud | B70: 7 | C70: 1 | D70: 1 | E70: 0 | F70: 1 | G70: 1 | H70: 12000000 | I70: 2 | J70: 0.14285714 | K70: 0 | L70: 0 | M70: 24 | N70: Tier 4 | O70: Sebastian Wouters — VP Network Operations; Maia Benson — Chief Business Officer; Rathna Sharad — CEO & Co-Founder; Rathna Sharad — CEO; Sharad Kylasam — VP Product | P70: VP Network Operations | Chief Business Officer | CEO & Co-Founder | Y70: todo | Z70: =(M70*Weights!$B$2) + (MIN(Q70,Weights!$B$5)*Weights!$B$3*(W70/100)*Weights!$B$4) | AA70: =IF(Z70= ,,RANK.EQ({pri_col_letter}{r},{pri_range},0))
A71: Costco | B71: 6 | C71: 0 | D71: 1 | E71: 0 | F71: 0 | G71: 3 | I71: 3 | J71: 0.16666667 | K71: 12 | L71: 25 | M71: 23 | N71: Tier 4 | O71: Scott Wibert — Supply Chain SA/Security; Brian McBride — Global IT/Innovation; Kate Domer — Innovation Analyst; Krissie Connors — Analyst - Innovation; Troy Ness — Director of Global Innovation | P71: Supply Chain SA/Security | Global IT/Innovation | Innovation Analyst | Y71: todo | Z71: =(M71*Weights!$B$2) + (MIN(Q71,Weights!$B$5)*Weights!$B$3*(W71/100)*Weights!$B$4) | AA71: =IF(Z71= ,,RANK.EQ({pri_col_letter}{r},{pri_range},0))
A72: Infor | B72: 6 | C72: 1 | D72: 1 | E72: 0 | F72: 1 | G72: 0 | I72: 1 | J72: 0.16666667 | K72: 0 | L72: 0 | M72: 23 | N72: Tier 4 | O72: Mike Herber — VP, Supply Chain Solutions; Doug Zahour — VP, Infor Nexus; Jason Simcox — VP, Infor Nexus; Jessica Reed — Sr. Account Manager; Luke Anderson — Sr. Account Manager | P72: VP, Supply Chain Solutions | VP, Infor Nexus | Sr. Account Manager | Y72: todo | Z72: =(M72*Weights!$B$2) + (MIN(Q72,Weights!$B$5)*Weights!$B$3*(W72/100)*Weights!$B$4) | AA72: =IF(Z72= ,,RANK.EQ({pri_col_letter}{r},{pri_range},0))
A73: Metro Supply Chain | B73: 6 | C73: 1 | D73: 1 | E73: 0 | F73: 1 | G73: 0 | I73: 1 | J73: 0.16666667 | K73: 0 | L73: 0 | M73: 23 | N73: Tier 4 | O73: Chris Galindo — President- Supply Chain Services; Sean Cowie — VP Customer Solutions; Pierre Lutfy — Chief Development Officer; Glenn Hunter — Senior Director Implementation Services; Monica Burger — Director Applications Implementation and Support | P73: President- Supply Chain Services | VP Customer Solutions | Chief Development Officer | Y73: todo | Z73: =(M73*Weights!$B$2) + (MIN(Q73,Weights!$B$5)*Weights!$B$3*(W73/100)*Weights!$B$4) | AA73: =IF(Z73= ,,RANK.EQ({pri_col_letter}{r},{pri_range},0))
A74: Neovia Logistics | B74: 6 | C74: 1 | D74: 1 | E74: 1 | F74: 2 | G74: 0 | I74: 2 | J74: 0.16666667 | K74: 0 | L74: 0 | M74: 23 | N74: Tier 4 | O74: Jacques Retief — Chief Operations Officer; Elaine Evans — Senior Global Procurement Manager; Mike Fahy — Chief Executive Officer; Bethany Peek — Communications Specialist; Dan Bombrys — Vice President Customer Success | P74: Chief Operations Officer | Chief Executive Officer | Senior Global Procurement Manager | Y74: todo | Z74: =(M74*Weights!$B$2) + (MIN(Q74,Weights!$B$5)*Weights!$B$3*(W74/100)*Weights!$B$4) | AA74: =IF(Z74= ,,RANK.EQ({pri_col_letter}{r},{pri_range},0))
A75: Manifest.eco | B75: 4 | C75: 1 | D75: 1 | E75: 0 | F75: 0 | G75: 0 | I75: 0 | J75: 0.25 | K75: 0 | L75: 0 | M75: 23 | N75: Tier 4 | O75: Max Stevens — SVP Fulfillment; Cole Wenzel — SVP Customer; George Wojciechowski — CEO; Robert Sixsmith — COO | P75: SVP Fulfillment | SVP Customer | CEO | Y75: todo | Z75: =(M75*Weights!$B$2) + (MIN(Q75,Weights!$B$5)*Weights!$B$3*(W75/100)*Weights!$B$4) | AA75: =IF(Z75= ,,RANK.EQ({pri_col_letter}{r},{pri_range},0))
A76: Crane Worldwide Logistics | B76: 3 | C76: 0 | D76: 0 | E76: 0 | F76: 0 | G76: 0 | H76: 1000000000 | I76: 0 | J76: 0 | K76: 0 | L76: 0 | M76: 23 | N76: Tier 4 | O76: Brannon Kuykendall — Chief Information Officer; Dylan Ross — CFO; Jared Crane — CEO | P76: CFO | CEO | Chief Information Officer | Y76: todo | Z76: =(M76*Weights!$B$2) + (MIN(Q76,Weights!$B$5)*Weights!$B$3*(W76/100)*Weights!$B$4) | AA76: =IF(Z76= ,,RANK.EQ({pri_col_letter}{r},{pri_range},0))
A77: Acuity Brands | B77: 2 | C77: 1 | D77: 1 | E77: 1 | F77: 0 | G77: 0 | I77: 0 | J77: 0.5 | K77: 0 | L77: 0 | M77: 23 | N77: Tier 4 | O77: Joe DeFrancesco — Head of Operations; Jeff Grossman — Head of Sourcing | P77: Head of Operations | Head of Sourcing | Y77: todo | Z77: =(M77*Weights!$B$2) + (MIN(Q77,Weights!$B$5)*Weights!$B$3*(W77/100)*Weights!$B$4) | AA77: =IF(Z77= ,,RANK.EQ({pri_col_letter}{r},{pri_range},0))
A78: Glīd | B78: 2 | C78: 1 | D78: 2 | E78: 0 | F78: 1 | G78: 0 | I78: 1 | J78: 1 | K78: 0 | L78: 0 | M78: 23 | N78: Tier 4 | O78: Ankit Malhotra — Head of Operations; Aaron Stieglitz — Sales & Operations Lead | P78: Head of Operations | Sales & Operations Lead | Y78: todo | Z78: =(M78*Weights!$B$2) + (MIN(Q78,Weights!$B$5)*Weights!$B$3*(W78/100)*Weights!$B$4) | AA78: =IF(Z78= ,,RANK.EQ({pri_col_letter}{r},{pri_range},0))
A79: Martinrea International | B79: 2 | C79: 1 | D79: 1 | E79: 1 | F79: 0 | G79: 0 | I79: 0 | J79: 0.5 | K79: 0 | L79: 0 | M79: 23 | N79: Tier 4 | O79: Megan Hunter — Executive Vice President Procurement and Supply Chain Operations; Rachel Handbury — Director of Sustainability | P79: Executive Vice President Procurement and Supply Chain Operations | Director of Sustainability | Y79: todo | Z79: =(M79*Weights!$B$2) + (MIN(Q79,Weights!$B$5)*Weights!$B$3*(W79/100)*Weights!$B$4) | AA79: =IF(Z79= ,,RANK.EQ({pri_col_letter}{r},{pri_range},0))
A80: Sifted | B80: 5 | C80: 1 | D80: 2 | E80: 0 | F80: 3 | G80: 0 | I80: 3 | J80: 0.4 | K80: 0 | L80: 0 | M80: 22 | N80: Tier 4 | O80: Heather Guerry — SVP Client Experience & Operations; Ed Ferrugia — Sr Logistics Intelligence Specialist; Jeremy Lee — Head of Sales; Nick Koontz — Enterprise Account Executive; Nick Giuliani — Director of Business Development & Partnerships | P80: SVP Client Experience & Operations | Sr Logistics Intelligence Specialist | Head of Sales | Y80: todo | Z80: =(M80*Weights!$B$2) + (MIN(Q80,Weights!$B$5)*Weights!$B$3*(W80/100)*Weights!$B$4) | AA80: =IF(Z80= ,,RANK.EQ({pri_col_letter}{r},{pri_range},0))
A81: Bandit Running | B81: 3 | C81: 1 | D81: 1 | E81: 0 | F81: 0 | G81: 0 | I81: 0 | J81: 0.33333333 | K81: 0 | L81: 0 | M81: 22 | N81: Tier 4 | O81: Emily Shaw — Head of Operations; Steven Barrett — Vice President; Anya Nayak — Operational Excellence and Strategy | P81: Head of Operations | Vice President | Operational Excellence and Strategy | Y81: todo | Z81: =(M81*Weights!$B$2) + (MIN(Q81,Weights!$B$5)*Weights!$B$3*(W81/100)*Weights!$B$4) | AA81: =IF(Z81= ,,RANK.EQ({pri_col_letter}{r},{pri_range},0))
A82: Bloomberg | B82: 3 | C82: 1 | D82: 1 | E82: 0 | F82: 0 | G82: 0 | I82: 0 | J82: 0.33333333 | K82: 0 | L82: 0 | M82: 22 | N82: Tier 4 | O82: Bruno Svanci — Head of Supply Chain Technology; Laura Curtis — Editor/Reporter; Spencer Soper — Tech Reporter | P82: Head of Supply Chain Technology | Tech Reporter | Editor/Reporter | Y82: todo | Z82: =(M82*Weights!$B$2) + (MIN(Q82,Weights!$B$5)*Weights!$B$3*(W82/100)*Weights!$B$4) | AA82: =IF(Z82= ,,RANK.EQ({pri_col_letter}{r},{pri_range},0))
A83: Dollar City | B83: 3 | C83: 1 | D83: 1 | E83: 0 | F83: 0 | G83: 0 | I83: 0 | J83: 0.33333333 | K83: 0 | L83: 0 | M83: 22 | N83: Tier 4 | O83: Nicolas Pombo — Supply Chain VP; Pierre Bouchet — International Trade & Compliance Director; Alejandro Cienfuegos — Replenishment Director | P83: Supply Chain VP | Replenishment Director | International Trade & Compliance Director | Y83: todo | Z83: =(M83*Weights!$B$2) + (MIN(Q83,Weights!$B$5)*Weights!$B$3*(W83/100)*Weights!$B$4) | AA83: =IF(Z83= ,,RANK.EQ({pri_col_letter}{r},{pri_range},0))
A84: Gallo | B84: 3 | C84: 1 | D84: 1 | E84: 0 | F84: 0 | G84: 0 | I84: 0 | J84: 0.33333333 | K84: 0 | L84: 0 | M84: 22 | N84: Tier 4 | O84: Nitin Murali — Vice President Supply Chain Excellence; Chad Clausen — Sr. Value Stream Manager; Mariel Zare — Senior Value Stream Manager | P84: Vice President Supply Chain Excellence | Sr. Value Stream Manager | Senior Value Stream Manager | Y84: todo | Z84: =(M84*Weights!$B$2) + (MIN(Q84,Weights!$B$5)*Weights!$B$3*(W84/100)*Weights!$B$4) | AA84: =IF(Z84= ,,RANK.EQ({pri_col_letter}{r},{pri_range},0))
A85: Goldman Sachs | B85: 3 | C85: 1 | D85: 1 | E85: 0 | F85: 0 | G85: 0 | I85: 0 | J85: 0.33333333 | K85: 0 | L85: 0 | M85: 22 | N85: Tier 4 | O85: Kevin Lynch — Head of Supply Chain Tech Investment Banking Coverage; Ben Fife — Vice President; Ariana Callender — Investor | P85: Head of Supply Chain Tech Investment Banking Coverage | Vice President | Investor | Y85: todo | Z85: =(M85*Weights!$B$2) + (MIN(Q85,Weights!$B$5)*Weights!$B$3*(W85/100)*Weights!$B$4) | AA85: =IF(Z85= ,,RANK.EQ({pri_col_letter}{r},{pri_range},0))
A86: McClain & Associates | B86: 3 | C86: 1 | D86: 1 | E86: 0 | F86: 0 | G86: 0 | I86: 0 | J86: 0.33333333 | K86: 0 | L86: 0 | M86: 22 | N86: Tier 4 | O86: Sean McClain — VP Operations; Rob Olsen — VP Business Develpment; Dan McClain — President | P86: VP Operations | VP Business Develpment | President | Y86: todo | Z86: =(M86*Weights!$B$2) + (MIN(Q86,Weights!$B$5)*Weights!$B$3*(W86/100)*Weights!$B$4) | AA86: =IF(Z86= ,,RANK.EQ({pri_col_letter}{r},{pri_range},0))
A87: Melrose | B87: 3 | C87: 1 | D87: 1 | E87: 0 | F87: 0 | G87: 0 | I87: 0 | J87: 0.33333333 | K87: 0 | L87: 0 | M87: 22 | N87: Tier 4 | O87: Mike DeLucia — VP of Operations; Dhaman Rakhra — Chief Executive Officer; Khalid Karim — Chief Technology Officer | P87: VP of Operations | Chief Executive Officer | Chief Technology Officer | Y87: todo | Z87: =(M87*Weights!$B$2) + (MIN(Q87,Weights!$B$5)*Weights!$B$3*(W87/100)*Weights!$B$4) | AA87: =IF(Z87= ,,RANK.EQ({pri_col_letter}{r},{pri_range},0))
A88: Spot Inc | B88: 3 | C88: 1 | D88: 1 | E88: 0 | F88: 0 | G88: 2 | I88: 2 | J88: 0.33333333 | K88: 0 | L88: 0 | M88: 22 | N88: Tier 4 | O88: Kreg Hunter — VP of Operations; Jake Wittmann — Product Owner; Sean Ward — Product Owner | P88: VP of Operations | Product Owner | Y88: todo | Z88: =(M88*Weights!$B$2) + (MIN(Q88,Weights!$B$5)*Weights!$B$3*(W88/100)*Weights!$B$4) | AA88: =IF(Z88= ,,RANK.EQ({pri_col_letter}{r},{pri_range},0))
... A101: ShipHero | B101: 4 | C101: 1 | D101: 1 | E101: 0 | F101: 1 | G101: 0 | I101: 1 | J101: 0.25 | K101: 0 | L101: 0 | M101: 21 | N101: Tier 4 | O101: Karen Schwartz — VP of Transportation; Aaron Rubin — CEO; Lara Pease — Carrier Strategist Manager; Alex Gorney — Enterprise Account Executive | P101: VP of Transportation | CEO | Carrier Strategist Manager | Y101: todo | Z101: =(M101*Weights!$B$2) + (MIN(Q101,Weights!$B$5)*Weights!$B$3*(W101/100)*Weights!$B$4) | AA101: =IF(Z101= ,,RANK.EQ({pri_col_letter}{r},{pri_range},0))
A102: Hellmann Worldwide Logistics | B102: 3 | C102: 0 | D102: 0 | E102: 0 | F102: 1 | G102: 0 | H102: 4306000000 | I102: 1 | J102: 0 | K102: 0 | L102: 0 | M102: 21 | N102: Tier 4 | O102: Alberto Mathia — SVP, Regional Head of Airfreight for Americas; Michel Heck — Global Innovation Manager; Daniel Hoehle — Senior Manager Business Development E-Commerce | P102: SVP, Regional Head of Airfreight for Americas | Global Innovation Manager | Senior Manager Business Development E-Commerce | Y102: todo | Z102: =(M102*Weights!$B$2) + (MIN(Q102,Weights!$B$5)*Weights!$B$3*(W102/100)*Weights!$B$4) | AA102: =IF(Z102= ,,RANK.EQ({pri_col_letter}{r},{pri_range},0))
A103: Beiersdorf | B103: 2 | C103: 1 | D103: 1 | E103: 0 | F103: 0 | G103: 0 | I103: 0 | J103: 0.5 | K103: 0 | L103: 0 | M103: 21 | N103: Tier 4 | O103: Michael Frey — Chief Supply Chain Officer; Lisa Dobrin — VP SC North America | P103: Chief Supply Chain Officer | VP SC North America | Y103: todo | Z103: =(M103*Weights!$B$2) + (MIN(Q103,Weights!$B$5)*Weights!$B$3*(W103/100)*Weights!$B$4) | AA103: =IF(Z103= ,,RANK.EQ({pri_col_letter}{r},{pri_range},0))
A104: California Innovations | B104: 2 | C104: 1 | D104: 1 | E104: 0 | F104: 0 | G104: 0 | I104: 0 | J104: 0.5 | K104: 0 | L104: 0 | M104: 21 | N104: Tier 4 | O104: Jesse Lydiatt — VP Supply Chain; Amanda Foisy — CFO | P104: VP Supply Chain | CFO | Y104: todo | Z104: =(M104*Weights!$B$2) + (MIN(Q104,Weights!$B$5)*Weights!$B$3*(W104/100)*Weights!$B$4) | AA104: =IF(Z104= ,,RANK.EQ({pri_col_letter}{r},{pri_range},0))
A105: Castlery | B105: 2 | C105: 1 | D105: 1 | E105: 0 | F105: 0 | G105: 0 | I105: 0 | J105: 0.5 | K105: 0 | L105: 0 | M105: 21 | N105: Tier 4 | O105: Carlos Harper — Head of North America Operations; Kellie Dawn Kivett — Carrier Management | P105: Head of North America Operations | Carrier Management | Y105: todo | Z105: =(M105*Weights!$B$2) + (MIN(Q105,Weights!$B$5)*Weights!$B$3*(W105/100)*Weights!$B$4) | AA105: =IF(Z105= ,,RANK.EQ({pri_col_letter}{r},{pri_range},0))
A106: Fear of God | B106: 2 | C106: 1 | D106: 1 | E106: 0 | F106: 0 | G106: 0 | I106: 0 | J106: 0.5 | K106: 0 | L106: 0 | M106: 21 | N106: Tier 4 | O106: Nadia Chohan — Vice President of Supply Chain; Santiago Garcia — Finance Manager | P106: Vice President of Supply Chain | Finance Manager | Y106: todo | Z106: =(M106*Weights!$B$2) + (MIN(Q106,Weights!$B$5)*Weights!$B$3*(W106/100)*Weights!$B$4) | AA106: =IF(Z106= ,,RANK.EQ({pri_col_letter}{r},{pri_range},0))
A107: Goodr | B107: 2 | C107: 1 | D107: 1 | E107: 0 | F107: 0 | G107: 0 | I107: 0 | J107: 0.5 | K107: 0 | L107: 0 | M107: 21 | N107: Tier 4 | O107: Greg Bicksler — VP of Operations; Toni Bianco — Planning Manager | P107: VP of Operations | Planning Manager | Y107: todo | Z107: =(M107*Weights!$B$2) + (MIN(Q107,Weights!$B$5)*Weights!$B$3*(W107/100)*Weights!$B$4) | AA107: =IF(Z107= ,,RANK.EQ({pri_col_letter}{r},{pri_range},0))
A108: Hello Fresh | B108: 2 | C108: 1 | D108: 1 | E108: 0 | F108: 0 | G108: 0 | I108: 0 | J108: 0.5 | K108: 0 | L108: 0 | M108: 21 | N108: Tier 4 | O108: Nunzio Di Savino — VP Logistics; Jenna Kirschner — Chief of Staff | P108: VP Logistics | Chief of Staff | Y108: todo | Z108: =(M108*Weights!$B$2) + (MIN(Q108,Weights!$B$5)*Weights!$B$3*(W108/100)*Weights!$B$4) | AA108: =IF(Z108= ,,RANK.EQ({pri_col_letter}{r},{pri_range},0))
A109: Huckberry | B109: 2 | C109: 1 | D109: 1 | E109: 0 | F109: 0 | G109: 0 | I109: 0 | J109: 0.5 | K109: 0 | L109: 0 | M109: 21 | N109: Tier 4 | O109: Nick Meister — VP, Operations; Ben Strand — Manager | P109: VP, Operations | Manager | Y109: todo | Z109: =(M109*Weights!$B$2) + (MIN(Q109,Weights!$B$5)*Weights!$B$3*(W109/100)*Weights!$B$4) | AA109: =IF(Z109= ,,RANK.EQ({pri_col_letter}{r},{pri_range},0))
A110: Joffroy | B110: 2 | C110: 1 | D110: 1 | E110: 0 | F110: 0 | G110: 0 | I110: 0 | J110: 0.5 | K110: 0 | L110: 0 | M110: 21 | N110: Tier 4 | O110: Mauricio Diaz — Head of Logistics; Eduardo Joffroy — CEO | P110: Head of Logistics | CEO | Y110: todo | Z110: =(M110*Weights!$B$2) + (MIN(Q110,Weights!$B$5)*Weights!$B$3*(W110/100)*Weights!$B$4) | AA110: =IF(Z110= ,,RANK.EQ({pri_col_letter}{r},{pri_range},0))
A111: MetaLearner | B111: 2 | C111: 1 | D111: 1 | E111: 0 | F111: 0 | G111: 0 | I111: 0 | J111: 0.5 | K111: 0 | L111: 0 | M111: 21 | N111: Tier 4 | O111: Jose Lama — Head of Operations; Kevin Good — CEO | P111: Head of Operations | CEO | Y111: todo | Z111: =(M111*Weights!$B$2) + (MIN(Q111,Weights!$B$5)*Weights!$B$3*(W111/100)*Weights!$B$4) | AA111: =IF(Z111= ,,RANK.EQ({pri_col_letter}{r},{pri_range},0))
A112: Midmo Inc | B112: 2 | C112: 1 | D112: 1 | E112: 0 | F112: 0 | G112: 0 | I112: 0 | J112: 0.5 | K112: 0 | L112: 0 | M112: 21 | N112: Tier 4 | O112: Jeremy Linder — Head of Strategic Operations; Gelika Bücker — Head of Partnerships | P112: Head of Strategic Operations | Head of Partnerships | Y112: todo | Z112: =(M112*Weights!$B$2) + (MIN(Q112,Weights!$B$5)*Weights!$B$3*(W112/100)*Weights!$B$4) | AA112: =IF(Z112= ,,RANK.EQ({pri_col_letter}{r},{pri_range},0))
A113: NMFTA | B113: 2 | C113: 1 | D113: 1 | E113: 0 | F113: 0 | G113: 0 | I113: 0 | J113: 0.5 | K113: 0 | L113: 0 | M113: 21 | N113: Tier 4 | O113: Keith Peterson — VP Operations; Joe Ohr — COO | P113: VP Operations | COO | Y113: todo | Z113: =(M113*Weights!$B$2) + (MIN(Q113,Weights!$B$5)*Weights!$B$3*(W113/100)*Weights!$B$4) | AA113: =IF(Z113= ,,RANK.EQ({pri_col_letter}{r},{pri_range},0))
A114: Novo Logistics | B114: 2 | C114: 1 | D114: 1 | E114: 0 | F114: 0 | G114: 0 | I114: 0 | J114: 0.5 | K114: 0 | L114: 0 | M114: 21 | N114: Tier 4 | O114: Jeff Hiott — VP of Operations; Greg Younghans — President | P114: VP of Operations | President | Y114: todo | Z114: =(M114*Weights!$B$2) + (MIN(Q114,Weights!$B$5)*Weights!$B$3*(W114/100)*Weights!$B$4) | AA114: =IF(Z114= ,,RANK.EQ({pri_col_letter}{r},{pri_range},0))
... A122: myMechanic, Inc. | B122: 2 | C122: 1 | D122: 1 | E122: 0 | F122: 0 | G122: 0 | I122: 0 | J122: 0.5 | K122: 0 | L122: 0 | M122: 21 | N122: Tier 4 | O122: Vic Zdor — VP of Operations; Alex Bezzubets — CEO | P122: VP of Operations | CEO | Y122: todo | Z122: =(M122*Weights!$B$2) + (MIN(Q122,Weights!$B$5)*Weights!$B$3*(W122/100)*Weights!$B$4) | AA122: =IF(Z122= ,,RANK.EQ({pri_col_letter}{r},{pri_range},0))
A123: Armada Supply Chain Solutions | B123: 1 | C123: 0 | D123: 0 | E123: 0 | F123: 0 | G123: 0 | H123: 5702000000 | I123: 0 | J123: 0 | K123: 0 | L123: 0 | M123: 21 | N123: Tier 4 | O123: Joe Wildes — Chief Innovation Officer | P123: Chief Innovation Officer | Y123: todo | Z123: =(M123*Weights!$B$2) + (MIN(Q123,Weights!$B$5)*Weights!$B$3*(W123/100)*Weights!$B$4) | AA123: =IF(Z123= ,,RANK.EQ({pri_col_letter}{r},{pri_range},0))
A124: Estes Express Lines | B124: 1 | C124: 0 | D124: 0 | E124: 0 | F124: 0 | G124: 0 | H124: 5100000000 | I124: 0 | J124: 0 | K124: 0 | L124: 0 | M124: 21 | N124: Tier 4 | O124: Todd Florence — CIO | P124: CIO | Y124: todo | Z124: =(M124*Weights!$B$2) + (MIN(Q124,Weights!$B$5)*Weights!$B$3*(W124/100)*Weights!$B$4) | AA124: =IF(Z124= ,,RANK.EQ({pri_col_letter}{r},{pri_range},0))
A125: Lineage | B125: 1 | C125: 0 | D125: 0 | E125: 0 | F125: 0 | G125: 0 | H125: 5340000000 | I125: 0 | J125: 0 | K125: 0 | L125: 0 | M125: 21 | N125: Tier 4 | O125: Jeff Rivera — Global Chief Operating Officer | P125: Global Chief Operating Officer | Y125: todo | Z125: =(M125*Weights!$B$2) + (MIN(Q125,Weights!$B$5)*Weights!$B$3*(W125/100)*Weights!$B$4) | AA125: =IF(Z125= ,,RANK.EQ({pri_col_letter}{r},{pri_range},0))
A126: Manhattan Associates | B126: 1 | C126: 0 | D126: 0 | E126: 0 | F126: 0 | G126: 1 | H126: 1042352000 | I126: 1 | J126: 0 | K126: 0 | L126: 0 | M126: 21 | N126: Tier 4 | O126: Bryant Smith — Director of Product Management | P126: Director of Product Management | Y126: todo | Z126: =(M126*Weights!$B$2) + (MIN(Q126,Weights!$B$5)*Weights!$B$3*(W126/100)*Weights!$B$4) | AA126: =IF(Z126= ,,RANK.EQ({pri_col_letter}{r},{pri_range},0))
A127: New Balance | B127: 1 | C127: 0 | D127: 0 | E127: 0 | F127: 0 | G127: 0 | H127: 7800000000 | I127: 0 | J127: 0 | K127: 0 | L127: 0 | M127: 21 | N127: Tier 4 | O127: Dave Wheeler — Chief Operating Officer | P127: Chief Operating Officer | Y127: todo | Z127: =(M127*Weights!$B$2) + (MIN(Q127,Weights!$B$5)*Weights!$B$3*(W127/100)*Weights!$B$4) | AA127: =IF(Z127= ,,RANK.EQ({pri_col_letter}{r},{pri_range},0))
A128: Energy Transportation Group | B128: 5 | C128: 1 | D128: 1 | E128: 0 | F128: 2 | G128: 0 | I128: 2 | J128: 0.2 | K128: 0 | L128: 0 | M128: 20 | N128: Tier 4 | O128: David Grassi — Executive Vice President of Commercial Operations; Michael Cinquino — President & CEO; Shawn Girard — CEO & CCO; Alex Ristevski — Vice President of Business Development; Joe Laviolette — Vice President of Business Development | P128: Executive Vice President of Commercial Operations | President & CEO | CEO & CCO | Y128: todo | Z128: =(M128*Weights!$B$2) + (MIN(Q128,Weights!$B$5)*Weights!$B$3*(W128/100)*Weights!$B$4) | AA128: =IF(Z128= ,,RANK.EQ({pri_col_letter}{r},{pri_range},0))
A129: Price Industries | B129: 4 | C129: 0 | D129: 4 | E129: 0 | F129: 0 | G129: 1 | I129: 1 | J129: 1 | K129: 0 | L129: 0 | M129: 20 | N129: Tier 4 | O129: Justen Collins — Director of Logistics; Kyle Donnelly — Corporate Logistics Manager; Chris Bloyd — Logistics Data Analyst; Gagant Thind — Director of Trade Compliance & Logistics | P129: Director of Logistics | Corporate Logistics Manager | Logistics Data Analyst | Y129: todo | Z129: =(M129*Weights!$B$2) + (MIN(Q129,Weights!$B$5)*Weights!$B$3*(W129/100)*Weights!$B$4) | AA129: =IF(Z129= ,,RANK.EQ({pri_col_letter}{r},{pri_range},0))
A130: Cobot | B130: 3 | C130: 1 | D130: 1 | E130: 0 | F130: 1 | G130: 1 | I130: 2 | J130: 0.33333333 | K130: 0 | L130: 0 | M130: 20 | N130: Tier 4 | O130: James Dietrich — Head of Logistics & Enterprise Sales; Jon Battles — VP of Technology; Taylor Richardson — Customer Solutions Engineer | P130: Head of Logistics & Enterprise Sales | VP of Technology | Customer Solutions Engineer | Y130: todo | Z130: =(M130*Weights!$B$2) + (MIN(Q130,Weights!$B$5)*Weights!$B$3*(W130/100)*Weights!$B$4) | AA130: =IF(Z130= ,,RANK.EQ({pri_col_letter}{r},{pri_range},0))
A131: Flock Freight | B131: 3 | C131: 1 | D131: 2 | E131: 0 | F131: 3 | G131: 0 | I131: 3 | J131: 0.66666667 | K131: 0 | L131: 0 | M131: 20 | N131: Tier 4 | O131: Kevin McMaster — SVP, Customer Success & Operations; Taylor Broderick — Director of Sales & Operations; Michael Munday — Director, Enterprise Sales | P131: SVP, Customer Success & Operations | Director of Sales & Operations | Director, Enterprise Sales | Y131: todo | Z131: =(M131*Weights!$B$2) + (MIN(Q131,Weights!$B$5)*Weights!$B$3*(W131/100)*Weights!$B$4) | AA131: =IF(Z131= ,,RANK.EQ({pri_col_letter}{r},{pri_range},0))
A132: RBW Logistics | B132: 3 | C132: 1 | D132: 1 | E132: 0 | F132: 1 | G132: 0 | I132: 1 | J132: 0.33333333 | K132: 0 | L132: 0 | M132: 20 | N132: Tier 4 | O132: Tony Huether — VP of Operations; Gregg Bansavage — CIO; Reed Loeffel — Director of Business Development | P132: VP of Operations | CIO | Director of Business Development | Y132: todo | Z132: =(M132*Weights!$B$2) + (MIN(Q132,Weights!$B$5)*Weights!$B$3*(W132/100)*Weights!$B$4) | AA132: =IF(Z132= ,,RANK.EQ({pri_col_letter}{r},{pri_range},0))
A133: Triage Partners | B133: 3 | C133: 1 | D133: 1 | E133: 0 | F133: 1 | G133: 0 | I133: 1 | J133: 0.33333333 | K133: 0 | L133: 0 | M133: 20 | N133: Tier 4 | O133: Christopher Bleess — VP, Integrated Supply Chain Division; Seana OLeary — Account Manager; Traci Parrish — Director, Business Development | P133: VP, Integrated Supply Chain Division | Account Manager | Director, Business Development | Y133: todo | Z133: =(M133*Weights!$B$2) + (MIN(Q133,Weights!$B$5)*Weights!$B$3*(W133/100)*Weights!$B$4) | AA133: =IF(Z133= ,,RANK.EQ({pri_col_letter}{r},{pri_range},0))
A134: arnata | B134: 3 | C134: 1 | D134: 1 | E134: 0 | F134: 1 | G134: 0 | I134: 1 | J134: 0.33333333 | K134: 0 | L134: 0 | M134: 20 | N134: Tier 4 | O134: Elim Kuk — Head of Operations; Georgy Melkonyan — CEO & Founder; Vlad Arakeylan — GTM | P134: Head of Operations | CEO & Founder | GTM | Y134: todo | Z134: =(M134*Weights!$B$2) + (MIN(Q134,Weights!$B$5)*Weights!$B$3*(W134/100)*Weights!$B$4) | AA134: =IF(Z134= ,,RANK.EQ({pri_col_letter}{r},{pri_range},0))
A135: 7-Eleven | B135: 1 | C135: 1 | D135: 1 | E135: 0 | F135: 0 | G135: 0 | I135: 0 | J135: 1 | K135: 0 | L135: 0 | M135: 20 | N135: Tier 4 | O135: Joshua Dolan — SVP Demand Chain & Logistics | P135: SVP Demand Chain & Logistics | Y135: todo | Z135: =(M135*Weights!$B$2) + (MIN(Q135,Weights!$B$5)*Weights!$B$3*(W135/100)*Weights!$B$4) | AA135: =IF(Z135= ,,RANK.EQ({pri_col_letter}{r},{pri_range},0))
A136: Acer | B136: 1 | C136: 1 | D136: 1 | E136: 0 | F136: 0 | G136: 0 | I136: 0 | J136: 1 | K136: 0 | L136: 0 | M136: 20 | N136: Tier 4 | O136: Joyce Cruts — VP Supply Chain & Operations | P136: VP Supply Chain & Operations | Y136: todo | Z136: =(M136*Weights!$B$2) + (MIN(Q136,Weights!$B$5)*Weights!$B$3*(W136/100)*Weights!$B$4) | AA136: =IF(Z136= ,,RANK.EQ({pri_col_letter}{r},{pri_range},0))
A137: Airbus | B137: 1 | C137: 1 | D137: 1 | E137: 0 | F137: 0 | G137: 0 | I137: 0 | J137: 1 | K137: 0 | L137: 0 | M137: 20 | N137: Tier 4 | O137: Shaneel Kalan — Head of Logistics - Americas | P137: Head of Logistics - Americas | Y137: todo | Z137: =(M137*Weights!$B$2) + (MIN(Q137,Weights!$B$5)*Weights!$B$3*(W137/100)*Weights!$B$4) | AA137: =IF(Z137= ,,RANK.EQ({pri_col_letter}{r},{pri_range},0))
A138: Albertsons Technology | B138: 1 | C138: 1 | D138: 1 | E138: 0 | F138: 0 | G138: 0 | I138: 0 | J138: 1 | K138: 0 | L138: 0 | M138: 20 | N138: Tier 4 | O138: Dave Newton — VP Supply Chain Technology | P138: VP Supply Chain Technology | Y138: todo | Z138: =(M138*Weights!$B$2) + (MIN(Q138,Weights!$B$5)*Weights!$B$3*(W138/100)*Weights!$B$4) | AA138: =IF(Z138= ,,RANK.EQ({pri_col_letter}{r},{pri_range},0))
A139: Alibaba.com | B139: 1 | C139: 1 | D139: 1 | E139: 0 | F139: 0 | G139: 0 | I139: 0 | J139: 1 | K139: 0 | L139: 0 | M139: 20 | N139: Tier 4 | O139: Yikun Shao — Head of NA Supply Chain | P139: Head of NA Supply Chain | Y139: todo | Z139: =(M139*Weights!$B$2) + (MIN(Q139,Weights!$B$5)*Weights!$B$3*(W139/100)*Weights!$B$4) | AA139: =IF(Z139= ,,RANK.EQ({pri_col_letter}{r},{pri_range},0))
... A278: SLS RFID | B278: 4 | C278: 1 | D278: 1 | E278: 0 | F278: 3 | G278: 0 | I278: 3 | J278: 0.25 | K278: 0 | L278: 0 | M278: 17 | N278: Tier 4 | O278: Rich Nemesi — General Manager, Supply Chain Visibility RFID; Alex Kottoor — Chief Revenue Officer; Laura Franckhauser — Director of Growth; Kyle Laslo — Director of Channel Sales | P278: General Manager, Supply Chain Visibility RFID | Chief Revenue Officer | Director of Growth | Y278: todo | Z278: =(M278*Weights!$B$2) + (MIN(Q278,Weights!$B$5)*Weights!$B$3*(W278/100)*Weights!$B$4) | AA278: =IF(Z278= ,,RANK.EQ({pri_col_letter}{r},{pri_range},0))
A279: C.R. England | B279: 3 | C279: 0 | D279: 1 | E279: 0 | F279: 1 | G279: 0 | H279: 500000000 | I279: 1 | J279: 0.33333333 | K279: 0 | L279: 0 | M279: 17 | N279: Tier 4 | O279: Zach England — COO; Jennifer Bryant — Director of Strategic Development; Alex Ikenberry — Director of Business Development - Dedicated, OTR, Intermodal & Mexico | P279: COO | Director of Strategic Development | Director of Business Development - Dedicated, OTR, Intermodal & Mexico | Y279: todo | Z279: =(M279*Weights!$B$2) + (MIN(Q279,Weights!$B$5)*Weights!$B$3*(W279/100)*Weights!$B$4) | AA279: =IF(Z279= ,,RANK.EQ({pri_col_letter}{r},{pri_range},0))
A280: Reckitt Benckiser | B280: 3 | C280: 0 | D280: 3 | E280: 1 | F280: 0 | G280: 0 | I280: 0 | J280: 1 | K280: 0 | L280: 0 | M280: 17 | N280: Tier 4 | O280: Gideon Steed — Director, Logistics Procurement; Courtney Rowan — Senior Manager, Transportation; Molly Reid — Senior Manager, Transportation | P280: Director, Logistics Procurement | Senior Manager, Transportation | Y280: todo | Z280: =(M280*Weights!$B$2) + (MIN(Q280,Weights!$B$5)*Weights!$B$3*(W280/100)*Weights!$B$4) | AA280: =IF(Z280= ,,RANK.EQ({pri_col_letter}{r},{pri_range},0))
A281: Flexport | B281: 21 | C281: 1 | D281: 1 | E281: 2 | F281: 8 | G281: 0 | I281: 8 | J281: 0.047619048 | K281: 12 | L281: 0 | M281: 16 | N281: Tier 4 | O281: Mike Castle — Head of Transportation and Parcel Strategy; Adam Parish — Director, Trucking Procurement; Huy Phan Hoang — Manager, Ocean Procurement; Alexis Boutet — VP, Global Head of Airfreight; Ted Boeglin — VP, Americas | P281: Head of Transportation and Parcel Strategy | VP, Global Head of Airfreight | VP, Americas | Y281: todo | Z281: =(M281*Weights!$B$2) + (MIN(Q281,Weights!$B$5)*Weights!$B$3*(W281/100)*Weights!$B$4) | AA281: =IF(Z281= ,,RANK.EQ({pri_col_letter}{r},{pri_range},0))
A282: ABB | B282: 4 | C282: 0 | D282: 3 | E282: 0 | F282: 0 | G282: 0 | I282: 0 | J282: 0.75 | K282: 0 | L282: 0 | M282: 16 | N282: Tier 4 | O282: Chad Brant — Director of Transportation; Bryan Tckett — Transportation Manager; Wesley Read — Domestic Transportation Specialist; Alva Green — Freight Specialist | P282: Director of Transportation | Transportation Manager | Domestic Transportation Specialist | Y282: todo | Z282: =(M282*Weights!$B$2) + (MIN(Q282,Weights!$B$5)*Weights!$B$3*(W282/100)*Weights!$B$4) | AA282: =IF(Z282= ,,RANK.EQ({pri_col_letter}{r},{pri_range},0))
A283: Aritzia | B283: 4 | C283: 0 | D283: 3 | E283: 0 | F283: 0 | G283: 0 | I283: 0 | J283: 0.75 | K283: 0 | L283: 0 | M283: 16 | N283: Tier 4 | O283: Lisa Fordyce — Director, Inbound Logistics; Ryan Yeung — Senior Director, Global Logistics; Jimmy Wong — Director, Supply Chain Technology; Vitaly Bekker — Manager, Carrier Performance | P283: Director, Inbound Logistics | Senior Director, Global Logistics | Director, Supply Chain Technology | Y283: todo | Z283: =(M283*Weights!$B$2) + (MIN(Q283,Weights!$B$5)*Weights!$B$3*(W283/100)*Weights!$B$4) | AA283: =IF(Z283= ,,RANK.EQ({pri_col_letter}{r},{pri_range},0))
A284: Boeing | B284: 4 | C284: 0 | D284: 3 | E284: 0 | F284: 0 | G284: 0 | I284: 0 | J284: 0.75 | K284: 0 | L284: 0 | M284: 16 | N284: Tier 4 | O284: David Ward — Cross dock/Logistics Network; Thomas Embleton — Senior Transportation Manager/Dedicated Fleet Management; Thomas Renowden — Transportation Management Systems/EDI; Raymond Quon — Provider Management | P284: Cross dock/Logistics Network | Senior Transportation Manager/Dedicated Fleet Management | Transportation Management Systems/EDI | Y284: todo | Z284: =(M284*Weights!$B$2) + (MIN(Q284,Weights!$B$5)*Weights!$B$3*(W284/100)*Weights!$B$4) | AA284: =IF(Z284= ,,RANK.EQ({pri_col_letter}{r},{pri_range},0))
A285: United Airlines | B285: 4 | C285: 0 | D285: 3 | E285: 0 | F285: 0 | G285: 0 | I285: 0 | J285: 0.75 | K285: 0 | L285: 0 | M285: 16 | N285: Tier 4 | O285: Dan Curley — Sr Analyst - Transportation; Tammy Terranova Gomez — Manager of Provisioning, End User Services, IMAC, Logistics and Depot; Max Clink — Senior Manager - Transportation & Logistics; Gwyn Peterson — Sr. Manager, International Trade Compliance | P285: Sr Analyst - Transportation | Manager of Provisioning, End User Services, IMAC, Logistics and Depot | Senior Manager - Transportation & Logistics | Y285: todo | Z285: =(M285*Weights!$B$2) + (MIN(Q285,Weights!$B$5)*Weights!$B$3*(W285/100)*Weights!$B$4) | AA285: =IF(Z285= ,,RANK.EQ({pri_col_letter}{r},{pri_range},0))
A286: FedEx | B286: 12 | C286: 0 | D286: 0 | E286: 0 | F286: 5 | G286: 3 | I286: 8 | J286: 0 | K286: 12 | L286: 25 | M286: 15 | N286: Tier 4 | O286: Stephanie Cannon — Vice President, Global Digital IT; Avi Slavin — Advisor; Chandler McCay — Global Program Strategy Advisor; Mike Gasik — Solutions Consultant Lead; Haley Martis — Event Manager | P286: Vice President, Global Digital IT | Principal, Corporate Strategy | Digital Product Fellow | Y286: todo | Z286: =(M286*Weights!$B$2) + (MIN(Q286,Weights!$B$5)*Weights!$B$3*(W286/100)*Weights!$B$4) | AA286: =IF(Z286= ,,RANK.EQ({pri_col_letter}{r},{pri_range},0))
A287: 1st Phorm | B287: 3 | C287: 0 | D287: 3 | E287: 0 | F287: 0 | G287: 0 | I287: 0 | J287: 1 | K287: 0 | L287: 0 | M287: 15 | N287: Tier 4 | O287: Brian Whiting — Director of Operations; Dakota Miller — Warehouse Manager; Josh Ward — Warehouse Manager | P287: Director of Operations | Warehouse Manager | Y287: todo | Z287: =(M287*Weights!$B$2) + (MIN(Q287,Weights!$B$5)*Weights!$B$3*(W287/100)*Weights!$B$4) | AA287: =IF(Z287= ,,RANK.EQ({pri_col_letter}{r},{pri_range},0))
A288: Allegiant Air | B288: 3 | C288: 0 | D288: 3 | E288: 0 | F288: 0 | G288: 0 | I288: 0 | J288: 1 | K288: 0 | L288: 0 | M288: 15 | N288: Tier 4 | O288: Christopher Smith — Trade & Logistics Analyst; Rawley Mims — Director Stores, Tools & Logistics; Sylvia Smith — Trade & Logistics Supervisor | P288: Trade & Logistics Analyst | Director Stores, Tools & Logistics | Trade & Logistics Supervisor | Y288: todo | Z288: =(M288*Weights!$B$2) + (MIN(Q288,Weights!$B$5)*Weights!$B$3*(W288/100)*Weights!$B$4) | AA288: =IF(Z288= ,,RANK.EQ({pri_col_letter}{r},{pri_range},0))
A289: Christian Louboutin | B289: 3 | C289: 0 | D289: 3 | E289: 0 | F289: 0 | G289: 0 | I289: 0 | J289: 1 | K289: 0 | L289: 0 | M289: 15 | N289: Tier 4 | O289: Meghan Wichern — Director of Logistics, The Americas; Korey Evering — Manager of 3PL Operations Americas; Samia Tebigui — Senior Manager of Transportation Americas | P289: Manager of 3PL Operations Americas | Senior Manager of Transportation Americas | Director of Logistics, The Americas | Y289: todo | Z289: =(M289*Weights!$B$2) + (MIN(Q289,Weights!$B$5)*Weights!$B$3*(W289/100)*Weights!$B$4) | AA289: =IF(Z289= ,,RANK.EQ({pri_col_letter}{r},{pri_range},0))
A290: G3 | B290: 3 | C290: 0 | D290: 3 | E290: 0 | F290: 0 | G290: 0 | I290: 0 | J290: 1 | K290: 0 | L290: 0 | M290: 15 | N290: Tier 4 | O290: Jerry Knight — Sr. Director Global Logistics; Jim Bolinger — Sr. Ops Manager; Nate Hunt — Sr. Ops Manager | P290: Sr. Director Global Logistics | Sr. Ops Manager | Y290: todo | Z290: =(M290*Weights!$B$2) + (MIN(Q290,Weights!$B$5)*Weights!$B$3*(W290/100)*Weights!$B$4) | AA290: =IF(Z290= ,,RANK.EQ({pri_col_letter}{r},{pri_range},0))
A291: John B. Sanfilippo & Son, Inc | B291: 3 | C291: 0 | D291: 3 | E291: 0 | F291: 0 | G291: 0 | I291: 0 | J291: 1 | K291: 0 | L291: 0 | M291: 15 | N291: Tier 4 | O291: Fatima Ayyad — Logistics Finance Analyst; Jon Fender — Director of Logistics; Dave Romano — Senior Logistics Manager | P291: Logistics Finance Analyst | Director of Logistics | Senior Logistics Manager | Y291: todo | Z291: =(M291*Weights!$B$2) + (MIN(Q291,Weights!$B$5)*Weights!$B$3*(W291/100)*Weights!$B$4) | AA291: =IF(Z291= ,,RANK.EQ({pri_col_letter}{r},{pri_range},0))
... A295: Niagara Bottling | B295: 4 | C295: 0 | D295: 1 | E295: 3 | F295: 0 | G295: 0 | I295: 0 | J295: 0.25 | K295: 0 | L295: 0 | M295: 14 | N295: Tier 4 | O295: Anup Pillay — Vice President of Procurement; Niraj Jha — Sr. Director of Logistics- Southwest; Fabio Baldassari — Sr Director of Procurement; Jose Gutierrez — Sr Manager of Procurement | P295: Vice President of Procurement | Sr. Director of Logistics- Southwest | Sr Director of Procurement | Y295: todo | Z295: =(M295*Weights!$B$2) + (MIN(Q295,Weights!$B$5)*Weights!$B$3*(W295/100)*Weights!$B$4) | AA295: =IF(Z295= ,,RANK.EQ({pri_col_letter}{r},{pri_range},0))
A296: Lazer Logistics | B296: 2 | C296: 0 | D296: 0 | E296: 0 | F296: 0 | G296: 0 | H296: 750000000 | I296: 0 | J296: 0 | K296: 0 | L296: 0 | M296: 14 | N296: Tier 4 | O296: Blaine Dirker — CTO; Chris Bennett — Vice President of EV, Energy, and Sustainability | P296: Vice President of EV, Energy, and Sustainability | CTO | Y296: todo | Z296: =(M296*Weights!$B$2) + (MIN(Q296,Weights!$B$5)*Weights!$B$3*(W296/100)*Weights!$B$4) | AA296: =IF(Z296= ,,RANK.EQ({pri_col_letter}{r},{pri_range},0))
A297: Carmax | B297: 3 | C297: 0 | D297: 2 | E297: 1 | F297: 0 | G297: 1 | I297: 1 | J297: 0.66666667 | K297: 0 | L297: 0 | M297: 13 | N297: Tier 4 | O297: Tyson Steele — Director of Procurement for Logistics; Christina Young — Director of Logistics Development and Innovation; Jessica Allison — Director, Product Management | P297: Director of Procurement for Logistics | Director of Logistics Development and Innovation | Director, Product Management | Y297: todo | Z297: =(M297*Weights!$B$2) + (MIN(Q297,Weights!$B$5)*Weights!$B$3*(W297/100)*Weights!$B$4) | AA297: =IF(Z297= ,,RANK.EQ({pri_col_letter}{r},{pri_range},0))
A298: Arc | B298: 1 | C298: 0 | D298: 0 | E298: 0 | F298: 0 | G298: 0 | H298: 369100000 | I298: 0 | J298: 0 | K298: 0 | L298: 0 | M298: 13 | N298: Tier 4 | O298: Mitch Lee — CEO & Co-Founder | P298: CEO & Co-Founder | Y298: todo | Z298: =(M298*Weights!$B$2) + (MIN(Q298,Weights!$B$5)*Weights!$B$3*(W298/100)*Weights!$B$4) | AA298: =IF(Z298= ,,RANK.EQ({pri_col_letter}{r},{pri_range},0))
A299: Ashdod Port Company | B299: 1 | C299: 0 | D299: 0 | E299: 0 | F299: 0 | G299: 0 | H299: 278000000 | I299: 0 | J299: 0 | K299: 0 | L299: 0 | M299: 13 | N299: Tier 4 | O299: Nissan Levy — CEO | P299: CEO | Y299: todo | Z299: =(M299*Weights!$B$2) + (MIN(Q299,Weights!$B$5)*Weights!$B$3*(W299/100)*Weights!$B$4) | AA299: =IF(Z299= ,,RANK.EQ({pri_col_letter}{r},{pri_range},0))
...

Sheet People Hitlist
A1: Name | B1: Category | C1: Job Title | D1: Company | E1: Country | F1: Qualified | G1: Revenue | H1: PersonScore | I1: is_ops | J1: is_exec | K1: is_exec_ops | L1: is_proc | M1: is_sales | N1: Company_Priority_Rank | O1: Company_Priority_Tier | P1: Owner | Q1: Outreach_Status | R1: Message_V1 | S1: Connect_Report_Link
A2: Sheetal Shah | B2: Speaker | C2: VP of Supply Chain and Chief Procurement Officer | D2: PPL Electric | H2: 37 | I2: TRUE | J2: TRUE | K2: TRUE | L2: TRUE | M2: FALSE | N2: =IFERROR(INDEX('Company Hitlist'!$AA:$AA,MATCH(D2,'Company Hitlist'!$A:$A,0)),) | O2: =IFERROR(INDEX('Company Hitlist'!$N:$N,MATCH(D2,'Company Hitlist'!$A:$A,0)),) | Q2: todo
A3: Jeff Adams | B3: Attendee | C3: VP of Strategic Sourcing & Inbound Logistics | D3: Apothecary Products | H3: 34 | I3: TRUE | J3: TRUE | K3: TRUE | L3: TRUE | M3: FALSE | N3: =IFERROR(INDEX('Company Hitlist'!$AA:$AA,MATCH(D3,'Company Hitlist'!$A:$A,0)),) | O3: =IFERROR(INDEX('Company Hitlist'!$N:$N,MATCH(D3,'Company Hitlist'!$A:$A,0)),) | Q3: todo
A4: Clark Howard | B4: Attendee | C4: Chief Supply Chain and Procurement Officer | D4: Butcher Box | H4: 34 | I4: TRUE | J4: TRUE | K4: TRUE | L4: TRUE | M4: FALSE | N4: =IFERROR(INDEX('Company Hitlist'!$AA:$AA,MATCH(D4,'Company Hitlist'!$A:$A,0)),) | O4: =IFERROR(INDEX('Company Hitlist'!$N:$N,MATCH(D4,'Company Hitlist'!$A:$A,0)),) | Q4: todo
A5: Terry Frizelle | B5: Attendee | C5: Head of Logistics Procurement | D5: Dell Technologies | F5: Yes | H5: 34 | I5: TRUE | J5: TRUE | K5: TRUE | L5: TRUE | M5: FALSE | N5: =IFERROR(INDEX('Company Hitlist'!$AA:$AA,MATCH(D5,'Company Hitlist'!$A:$A,0)),) | O5: =IFERROR(INDEX('Company Hitlist'!$N:$N,MATCH(D5,'Company Hitlist'!$A:$A,0)),) | Q5: todo
A6: Randy Pappal | B6: Attendee | C6: VP Purchasing and Supply Chain | D6: Gentex Corporation | H6: 34 | I6: TRUE | J6: TRUE | K6: TRUE | L6: TRUE | M6: FALSE | N6: =IFERROR(INDEX('Company Hitlist'!$AA:$AA,MATCH(D6,'Company Hitlist'!$A:$A,0)),) | O6: =IFERROR(INDEX('Company Hitlist'!$N:$N,MATCH(D6,'Company Hitlist'!$A:$A,0)),) | Q6: todo
A7: Jamie Hess | B7: Attendee | C7: VP, Global Transportation Procurement | D7: KBX | H7: 34 | I7: TRUE | J7: TRUE | K7: TRUE | L7: TRUE | M7: FALSE | N7: =IFERROR(INDEX('Company Hitlist'!$AA:$AA,MATCH(D7,'Company Hitlist'!$A:$A,0)),) | O7: =IFERROR(INDEX('Company Hitlist'!$N:$N,MATCH(D7,'Company Hitlist'!$A:$A,0)),) | Q7: todo
A8: Samia Kaci | B8: Attendee | C8: Vice President of Sourcing and Supply Chain AVD | D8: Legrand | H8: 34 | I8: TRUE | J8: TRUE | K8: TRUE | L8: TRUE | M8: FALSE | N8: =IFERROR(INDEX('Company Hitlist'!$AA:$AA,MATCH(D8,'Company Hitlist'!$A:$A,0)),) | O8: =IFERROR(INDEX('Company Hitlist'!$N:$N,MATCH(D8,'Company Hitlist'!$A:$A,0)),) | Q8: todo
A9: Megan Hunter | B9: Attendee | C9: Executive Vice President Procurement and Supply Chain Operations | D9: Martinrea International | H9: 34 | I9: TRUE | J9: TRUE | K9: TRUE | L9: TRUE | M9: FALSE | N9: =IFERROR(INDEX('Company Hitlist'!$AA:$AA,MATCH(D9,'Company Hitlist'!$A:$A,0)),) | O9: =IFERROR(INDEX('Company Hitlist'!$N:$N,MATCH(D9,'Company Hitlist'!$A:$A,0)),) | Q9: todo
A10: Chris Huggins | B10: Attendee | C10: Head of Logistics and Procurement | D10: Operation BBQ Relief | E10: United States | H10: 34 | I10: TRUE | J10: TRUE | K10: TRUE | L10: TRUE | M10: FALSE | N10: =IFERROR(INDEX('Company Hitlist'!$AA:$AA,MATCH(D10,'Company Hitlist'!$A:$A,0)),) | O10: =IFERROR(INDEX('Company Hitlist'!$N:$N,MATCH(D10,'Company Hitlist'!$A:$A,0)),) | Q10: todo
A11: Mohamed Saleh | B11: Attendee | C11: Head of Logistics & Real Estate Sourcing & Supply Chain | D11: Owens Corning | H11: 34 | I11: TRUE | J11: TRUE | K11: TRUE | L11: TRUE | M11: FALSE | N11: =IFERROR(INDEX('Company Hitlist'!$AA:$AA,MATCH(D11,'Company Hitlist'!$A:$A,0)),) | O11: =IFERROR(INDEX('Company Hitlist'!$N:$N,MATCH(D11,'Company Hitlist'!$A:$A,0)),) | Q11: todo
A12: Miguel Miciano | B12: Attendee | C12: SVP Procurement & Logistics | D12: Pomona Farming | H12: 34 | I12: TRUE | J12: TRUE | K12: TRUE | L12: TRUE | M12: FALSE | N12: =IFERROR(INDEX('Company Hitlist'!$AA:$AA,MATCH(D12,'Company Hitlist'!$A:$A,0)),) | O12: =IFERROR(INDEX('Company Hitlist'!$N:$N,MATCH(D12,'Company Hitlist'!$A:$A,0)),) | Q12: todo
A13: Lance Starks | B13: Attendee | C13: Vice President - Global Supply Chain & Sourcing | D13: Shaw Industries | H13: 34 | I13: TRUE | J13: TRUE | K13: TRUE | L13: TRUE | M13: FALSE | N13: =IFERROR(INDEX('Company Hitlist'!$AA:$AA,MATCH(D13,'Company Hitlist'!$A:$A,0)),) | O13: =IFERROR(INDEX('Company Hitlist'!$N:$N,MATCH(D13,'Company Hitlist'!$A:$A,0)),) | Q13: todo
A14: Andrew Sylling | B14: Attendee | C14: Head of Procurement, Logistics North America | D14: Unilever | H14: 34 | I14: TRUE | J14: TRUE | K14: TRUE | L14: TRUE | M14: FALSE | N14: =IFERROR(INDEX('Company Hitlist'!$AA:$AA,MATCH(D14,'Company Hitlist'!$A:$A,0)),) | O14: =IFERROR(INDEX('Company Hitlist'!$N:$N,MATCH(D14,'Company Hitlist'!$A:$A,0)),) | Q14: todo
A15: Sarah Clarke | B15: Speaker | C15: Chief Supply Chain & Technology Officer | D15: AEO Inc | H15: 29 | I15: TRUE | J15: TRUE | K15: TRUE | L15: FALSE | M15: FALSE | N15: =IFERROR(INDEX('Company Hitlist'!$AA:$AA,MATCH(D15,'Company Hitlist'!$A:$A,0)),) | O15: =IFERROR(INDEX('Company Hitlist'!$N:$N,MATCH(D15,'Company Hitlist'!$A:$A,0)),) | Q15: todo
A16: Joyce Cruts | B16: Speaker | C16: VP Supply Chain & Operations | D16: Acer | H16: 29 | I16: TRUE | J16: TRUE | K16: TRUE | L16: FALSE | M16: FALSE | N16: =IFERROR(INDEX('Company Hitlist'!$AA:$AA,MATCH(D16,'Company Hitlist'!$A:$A,0)),) | O16: =IFERROR(INDEX('Company Hitlist'!$N:$N,MATCH(D16,'Company Hitlist'!$A:$A,0)),) | Q16: todo
A17: Rasheed Mohamad | B17: Speaker | C17: EVP, Global Operations & Business Technology | D17: Alcatel-Lucent Enterprise | F17: Yes | G17: $1.2B (2024 est.; projected $1.3B in 2025) | H17: 29 | I17: TRUE | J17: TRUE | K17: TRUE | L17: FALSE | M17: FALSE | N17: =IFERROR(INDEX('Company Hitlist'!$AA:$AA,MATCH(D17,'Company Hitlist'!$A:$A,0)),) | O17: =IFERROR(INDEX('Company Hitlist'!$N:$N,MATCH(D17,'Company Hitlist'!$A:$A,0)),) | Q17: todo
A18: Linda Babilo | B18: Speaker | C18: Vice President, Global Supply Chain | D18: Arlon Graphics | H18: 29 | I18: TRUE | J18: TRUE | K18: TRUE | L18: FALSE | M18: FALSE | N18: =IFERROR(INDEX('Company Hitlist'!$AA:$AA,MATCH(D18,'Company Hitlist'!$A:$A,0)),) | O18: =IFERROR(INDEX('Company Hitlist'!$N:$N,MATCH(D18,'Company Hitlist'!$A:$A,0)),) | Q18: todo
A19: Gary Horsfield | B19: Speaker | C19: Chief Supply Chain Officer | D19: BIC | H19: 29 | I19: TRUE | J19: TRUE | K19: TRUE | L19: FALSE | M19: FALSE | N19: =IFERROR(INDEX('Company Hitlist'!$AA:$AA,MATCH(D19,'Company Hitlist'!$A:$A,0)),) | O19: =IFERROR(INDEX('Company Hitlist'!$N:$N,MATCH(D19,'Company Hitlist'!$A:$A,0)),) | Q19: todo
A20: Rick Duley | B20: Speaker | C20: SVP Supply Chain | D20: Babylist | H20: 29 | I20: TRUE | J20: TRUE | K20: TRUE | L20: FALSE | M20: FALSE | N20: =IFERROR(INDEX('Company Hitlist'!$AA:$AA,MATCH(D20,'Company Hitlist'!$A:$A,0)),) | O20: =IFERROR(INDEX('Company Hitlist'!$N:$N,MATCH(D20,'Company Hitlist'!$A:$A,0)),) | Q20: todo
A21: Michael Frey | B21: Speaker | C21: Chief Supply Chain Officer | D21: Beiersdorf | H21: 29 | I21: TRUE | J21: TRUE | K21: TRUE | L21: FALSE | M21: FALSE | N21: =IFERROR(INDEX('Company Hitlist'!$AA:$AA,MATCH(D21,'Company Hitlist'!$A:$A,0)),) | O21: =IFERROR(INDEX('Company Hitlist'!$N:$N,MATCH(D21,'Company Hitlist'!$A:$A,0)),) | Q21: todo
A22: Gina Seit | B22: Speaker | C22: SVP, Operations | D22: Branch Furniture | F22: Yes | G22: $10M (2024 est.; projected $12M in 2025) | H22: 29 | I22: TRUE | J22: TRUE | K22: TRUE | L22: FALSE | M22: FALSE | N22: =IFERROR(INDEX('Company Hitlist'!$AA:$AA,MATCH(D22,'Company Hitlist'!$A:$A,0)),) | O22: =IFERROR(INDEX('Company Hitlist'!$N:$N,MATCH(D22,'Company Hitlist'!$A:$A,0)),) | Q22: todo
A23: Brad Blizzard | B23: Speaker | C23: Former VP, Logistics Operations & Product Delivery | D23: Bridgestone Americas | H23: 29 | I23: TRUE | J23: TRUE | K23: TRUE | L23: FALSE | M23: FALSE | N23: =IFERROR(INDEX('Company Hitlist'!$AA:$AA,MATCH(D23,'Company Hitlist'!$A:$A,0)),) | O23: =IFERROR(INDEX('Company Hitlist'!$N:$N,MATCH(D23,'Company Hitlist'!$A:$A,0)),) | Q23: todo
A24: Jeff Vertun | B24: Speaker | C24: SVP Global Supply Chain Collective | D24: CBRE | E24: United States | H24: 29 | I24: TRUE | J24: TRUE | K24: TRUE | L24: FALSE | M24: FALSE | N24: =IFERROR(INDEX('Company Hitlist'!$AA:$AA,MATCH(D24,'Company Hitlist'!$A:$A,0)),) | O24: =IFERROR(INDEX('Company Hitlist'!$N:$N,MATCH(D24,'Company Hitlist'!$A:$A,0)),) | Q24: todo
A25: Jesse Lydiatt | B25: Speaker | C25: VP Supply Chain | D25: California Innovations | E25: Canada | H25: 29 | I25: TRUE | J25: TRUE | K25: TRUE | L25: FALSE | M25: FALSE | N25: =IFERROR(INDEX('Company Hitlist'!$AA:$AA,MATCH(D25,'Company Hitlist'!$A:$A,0)),) | O25: =IFERROR(INDEX('Company Hitlist'!$N:$N,MATCH(D25,'Company Hitlist'!$A:$A,0)),) | Q25: todo
A26: Marc Kalmes | B26: Speaker | C26: SVP Global Supply Chain | D26: ChampionX | H26: 29 | I26: TRUE | J26: TRUE | K26: TRUE | L26: FALSE | M26: FALSE | N26: =IFERROR(INDEX('Company Hitlist'!$AA:$AA,MATCH(D26,'Company Hitlist'!$A:$A,0)),) | O26: =IFERROR(INDEX('Company Hitlist'!$N:$N,MATCH(D26,'Company Hitlist'!$A:$A,0)),) | Q26: todo
A27: Carlos Ruiz | B27: Speaker | C27: EVP, Chief Supply Chain Officer | D27: Church & Dwight | H27: 29 | I27: TRUE | J27: TRUE | K27: TRUE | L27: FALSE | M27: FALSE | N27: =IFERROR(INDEX('Company Hitlist'!$AA:$AA,MATCH(D27,'Company Hitlist'!$A:$A,0)),) | O27: =IFERROR(INDEX('Company Hitlist'!$N:$N,MATCH(D27,'Company Hitlist'!$A:$A,0)),) | Q27: todo
A28: Amalia Londono | B28: Speaker | C28: EVP End to End Supply Chain North America | D28: Colgate-Palmolive | E28: United States | H28: 29 | I28: TRUE | J28: TRUE | K28: TRUE | L28: FALSE | M28: FALSE | N28: =IFERROR(INDEX('Company Hitlist'!$AA:$AA,MATCH(D28,'Company Hitlist'!$A:$A,0)),) | O28: =IFERROR(INDEX('Company Hitlist'!$N:$N,MATCH(D28,'Company Hitlist'!$A:$A,0)),) | Q28: todo
A29: Rick Goe | B29: Speaker | C29: SVP, Supply Chain | D29: Distribution Management | H29: 29 | I29: TRUE | J29: TRUE | K29: TRUE | L29: FALSE | M29: FALSE | N29: =IFERROR(INDEX('Company Hitlist'!$AA:$AA,MATCH(D29,'Company Hitlist'!$A:$A,0)),) | O29: =IFERROR(INDEX('Company Hitlist'!$N:$N,MATCH(D29,'Company Hitlist'!$A:$A,0)),) | Q29: todo
A30: Rod West | B30: Speaker | C30: EVP, Global Supply Chain | D30: Dollar General | H30: 29 | I30: TRUE | J30: TRUE | K30: TRUE | L30: FALSE | M30: FALSE | N30: =IFERROR(INDEX('Company Hitlist'!$AA:$AA,MATCH(D30,'Company Hitlist'!$A:$A,0)),) | O30: =IFERROR(INDEX('Company Hitlist'!$N:$N,MATCH(D30,'Company Hitlist'!$A:$A,0)),) | Q30: todo
A31: Toni Buhrke | B31: Speaker | C31: VP of Engineering and Operations | D31: Dot Ai | F31: Yes | H31: 29 | I31: TRUE | J31: TRUE | K31: TRUE | L31: FALSE | M31: FALSE | N31: =IFERROR(INDEX('Company Hitlist'!$AA:$AA,MATCH(D31,'Company Hitlist'!$A:$A,0)),) | O31: =IFERROR(INDEX('Company Hitlist'!$N:$N,MATCH(D31,'Company Hitlist'!$A:$A,0)),) | Q31: todo
A32: Miguel Martins da Silva | B32: Speaker | C32: Group Chief Supply Chain Officer | D32: Dr. Max BDC | H32: 29 | I32: TRUE | J32: TRUE | K32: TRUE | L32: FALSE | M32: FALSE | N32: =IFERROR(INDEX('Company Hitlist'!$AA:$AA,MATCH(D32,'Company Hitlist'!$A:$A,0)),) | O32: =IFERROR(INDEX('Company Hitlist'!$N:$N,MATCH(D32,'Company Hitlist'!$A:$A,0)),) | Q32: todo
A33: Sachin Mariguddi | B33: Speaker | C33: Chief Supply Chain Officer, Americas | D33: Elida Beauty | H33: 29 | I33: TRUE | J33: TRUE | K33: TRUE | L33: FALSE | M33: FALSE | N33: =IFERROR(INDEX('Company Hitlist'!$AA:$AA,MATCH(D33,'Company Hitlist'!$A:$A,0)),) | O33: =IFERROR(INDEX('Company Hitlist'!$N:$N,MATCH(D33,'Company Hitlist'!$A:$A,0)),) | Q33: todo
A34: Julian VanErlach | B34: Speaker | C34: SVP, Global Supply Chain & Customer Service | D34: FabFitFun | H34: 29 | I34: TRUE | J34: TRUE | K34: TRUE | L34: FALSE | M34: FALSE | N34: =IFERROR(INDEX('Company Hitlist'!$AA:$AA,MATCH(D34,'Company Hitlist'!$A:$A,0)),) | O34: =IFERROR(INDEX('Company Hitlist'!$N:$N,MATCH(D34,'Company Hitlist'!$A:$A,0)),) | Q34: todo
A35: Michael Gambino | B35: Speaker | C35: VP Operations | D35: Fasteners Inc | F35: Yes | G35: $50M (2024 est.; projected $55M in 2025) | H35: 29 | I35: TRUE | J35: TRUE | K35: TRUE | L35: FALSE | M35: FALSE | N35: =IFERROR(INDEX('Company Hitlist'!$AA:$AA,MATCH(D35,'Company Hitlist'!$A:$A,0)),) | O35: =IFERROR(INDEX('Company Hitlist'!$N:$N,MATCH(D35,'Company Hitlist'!$A:$A,0)),) | Q35: todo
A36: Rebecca Linz | B36: Speaker | C36: VP of Supply Chain | D36: Force of Nature Meats | H36: 29 | I36: TRUE | J36: TRUE | K36: TRUE | L36: FALSE | M36: FALSE | N36: =IFERROR(INDEX('Company Hitlist'!$AA:$AA,MATCH(D36,'Company Hitlist'!$A:$A,0)),) | O36: =IFERROR(INDEX('Company Hitlist'!$N:$N,MATCH(D36,'Company Hitlist'!$A:$A,0)),) | Q36: todo
A37: Douglas Cantriel | B37: Speaker | C37: Head of North American Transportation & Modernization | D37: Ford Motor Company | H37: 29 | I37: TRUE | J37: TRUE | K37: TRUE | L37: FALSE | M37: FALSE | N37: =IFERROR(INDEX('Company Hitlist'!$AA:$AA,MATCH(D37,'Company Hitlist'!$A:$A,0)),) | O37: =IFERROR(INDEX('Company Hitlist'!$N:$N,MATCH(D37,'Company Hitlist'!$A:$A,0)),) | Q37: todo
A38: Jamie Saucedo | B38: Speaker | C38: Vice President, Business Operations | D38: GXO | F38: Yes | G38: $10.4B (2024; projected $11B in 2025) | H38: 29 | I38: TRUE | J38: TRUE | K38: TRUE | L38: FALSE | M38: FALSE | N38: =IFERROR(INDEX('Company Hitlist'!$AA:$AA,MATCH(D38,'Company Hitlist'!$A:$A,0)),) | O38: =IFERROR(INDEX('Company Hitlist'!$N:$N,MATCH(D38,'Company Hitlist'!$A:$A,0)),) | Q38: todo
A39: Mohamed El Shami | B39: Speaker | C39: Chief Supply Chain Officer | D39: Garlock Printing & Converting | H39: 29 | I39: TRUE | J39: TRUE | K39: TRUE | L39: FALSE | M39: FALSE | N39: =IFERROR(INDEX('Company Hitlist'!$AA:$AA,MATCH(D39,'Company Hitlist'!$A:$A,0)),) | O39: =IFERROR(INDEX('Company Hitlist'!$N:$N,MATCH(D39,'Company Hitlist'!$A:$A,0)),) | Q39: todo
A40: Christopher Longhito | B40: Speaker | C40: SVP & Chief Supply Chain Officer | D40: Global Industrial Company | H40: 29 | I40: TRUE | J40: TRUE | K40: TRUE | L40: FALSE | M40: FALSE | N40: =IFERROR(INDEX('Company Hitlist'!$AA:$AA,MATCH(D40,'Company Hitlist'!$A:$A,0)),) | O40: =IFERROR(INDEX('Company Hitlist'!$N:$N,MATCH(D40,'Company Hitlist'!$A:$A,0)),) | Q40: todo
A41: Kinta Gates | B41: Speaker | C41: VP, Supply Chain and Operations | D41: Glossier | E41: United States | H41: 29 | I41: TRUE | J41: TRUE | K41: TRUE | L41: FALSE | M41: FALSE | N41: =IFERROR(INDEX('Company Hitlist'!$AA:$AA,MATCH(D41,'Company Hitlist'!$A:$A,0)),) | O41: =IFERROR(INDEX('Company Hitlist'!$N:$N,MATCH(D41,'Company Hitlist'!$A:$A,0)),) | Q41: todo
A42: Ian Kinne | B42: Speaker | C42: Vice President, Logistics Innovation & Investments | D42: Hillwood, a Perot Company | H42: 29 | I42: TRUE | J42: TRUE | K42: TRUE | L42: FALSE | M42: FALSE | N42: =IFERROR(INDEX('Company Hitlist'!$AA:$AA,MATCH(D42,'Company Hitlist'!$A:$A,0)),) | O42: =IFERROR(INDEX('Company Hitlist'!$N:$N,MATCH(D42,'Company Hitlist'!$A:$A,0)),) | Q42: todo
A43: Ajay Singh | B43: Speaker | C43: Chief Supply Chain Officer | D43: Hindustan Platinum | H43: 29 | I43: TRUE | J43: TRUE | K43: TRUE | L43: FALSE | M43: FALSE | N43: =IFERROR(INDEX('Company Hitlist'!$AA:$AA,MATCH(D43,'Company Hitlist'!$A:$A,0)),) | O43: =IFERROR(INDEX('Company Hitlist'!$N:$N,MATCH(D43,'Company Hitlist'!$A:$A,0)),) | Q43: todo
A44: Amanda Lorenz | B44: Speaker | C44: EVP, Operations | D44: Hugh & Grace | F44: Yes | H44: 29 | I44: TRUE | J44: TRUE | K44: TRUE | L44: FALSE | M44: FALSE | N44: =IFERROR(INDEX('Company Hitlist'!$AA:$AA,MATCH(D44,'Company Hitlist'!$A:$A,0)),) | O44: =IFERROR(INDEX('Company Hitlist'!$N:$N,MATCH(D44,'Company Hitlist'!$A:$A,0)),) | Q44: todo
A45: Mike Herber | B45: Speaker | C45: VP, Supply Chain Solutions | D45: Infor | H45: 29 | I45: TRUE | J45: TRUE | K45: TRUE | L45: FALSE | M45: FALSE | N45: =IFERROR(INDEX('Company Hitlist'!$AA:$AA,MATCH(D45,'Company Hitlist'!$A:$A,0)),) | O45: =IFERROR(INDEX('Company Hitlist'!$N:$N,MATCH(D45,'Company Hitlist'!$A:$A,0)),) | Q45: todo
A46: Wendy Spratt | B46: Speaker | C46: Head of Global Supply Chain | D46: Intel | H46: 29 | I46: TRUE | J46: TRUE | K46: TRUE | L46: FALSE | M46: FALSE | N46: =IFERROR(INDEX('Company Hitlist'!$AA:$AA,MATCH(D46,'Company Hitlist'!$A:$A,0)),) | O46: =IFERROR(INDEX('Company Hitlist'!$N:$N,MATCH(D46,'Company Hitlist'!$A:$A,0)),) | Q46: todo
A47: Bineetha Balakrishnan | B47: Speaker | C47: VP, Global Transportation & Trade Operations | D47: Johnson & Johnson | F47: Yes | G47: $85B (2024; projected $88B in 2025) | H47: 29 | I47: TRUE | J47: TRUE | K47: TRUE | L47: FALSE | M47: FALSE | N47: =IFERROR(INDEX('Company Hitlist'!$AA:$AA,MATCH(D47,'Company Hitlist'!$A:$A,0)),) | O47: =IFERROR(INDEX('Company Hitlist'!$N:$N,MATCH(D47,'Company Hitlist'!$A:$A,0)),) | Q47: todo
A48: Martijn Cillessen | B48: Speaker | C48: General Manager Supply Chain Management | D48: KYOCERA Document Solutions Europe Management BV | E48: Netherlands | H48: 29 | I48: TRUE | J48: TRUE | K48: TRUE | L48: FALSE | M48: FALSE | N48: =IFERROR(INDEX('Company Hitlist'!$AA:$AA,MATCH(D48,'Company Hitlist'!$A:$A,0)),) | O48: =IFERROR(INDEX('Company Hitlist'!$N:$N,MATCH(D48,'Company Hitlist'!$A:$A,0)),) | Q48: todo
A49: Meri Stevens | B49: Speaker | C49: Chief Operations Officer | D49: Kenvue | F49: Yes | G49: $15.5B (2024; projected $16B in 2025) | H49: 29 | I49: TRUE | J49: TRUE | K49: TRUE | L49: FALSE | M49: FALSE | N49: =IFERROR(INDEX('Company Hitlist'!$AA:$AA,MATCH(D49,'Company Hitlist'!$A:$A,0)),) | O49: =IFERROR(INDEX('Company Hitlist'!$N:$N,MATCH(D49,'Company Hitlist'!$A:$A,0)),) | Q49: todo
A50: Jimmy Cummings | B50: Speaker | C50: Vice President, Operations | D50: Kosas | F50: Yes | G50: $50M (2024 est.; projected $55M in 2025) | H50: 29 | I50: TRUE | J50: TRUE | K50: TRUE | L50: FALSE | M50: FALSE | N50: =IFERROR(INDEX('Company Hitlist'!$AA:$AA,MATCH(D50,'Company Hitlist'!$A:$A,0)),) | O50: =IFERROR(INDEX('Company Hitlist'!$N:$N,MATCH(D50,'Company Hitlist'!$A:$A,0)),) | Q50: todo
A51: Sacni Leon | B51: Speaker | C51: Head of DTX Ops, Reverse Logistics & Circularity Operations | D51: Logitech | E51: United States | H51: 29 | I51: TRUE | J51: TRUE | K51: TRUE | L51: FALSE | M51: FALSE | N51: =IFERROR(INDEX('Company Hitlist'!$AA:$AA,MATCH(D51,'Company Hitlist'!$A:$A,0)),) | O51: =IFERROR(INDEX('Company Hitlist'!$N:$N,MATCH(D51,'Company Hitlist'!$A:$A,0)),) | Q51: todo
A52: David Chen | B52: Speaker | C52: Chief Supply Chain Officer | D52: Mark Cuban Cost Plus Drug Company, PBC | H52: 29 | I52: TRUE | J52: TRUE | K52: TRUE | L52: FALSE | M52: FALSE | N52: =IFERROR(INDEX('Company Hitlist'!$AA:$AA,MATCH(D52,'Company Hitlist'!$A:$A,0)),) | O52: =IFERROR(INDEX('Company Hitlist'!$N:$N,MATCH(D52,'Company Hitlist'!$A:$A,0)),) | Q52: todo
A53: Mark Aquilina | B53: Speaker | C53: Global Head B2B Transportation | D53: Mastercard | H53: 29 | I53: TRUE | J53: TRUE | K53: TRUE | L53: FALSE | M53: FALSE | N53: =IFERROR(INDEX('Company Hitlist'!$AA:$AA,MATCH(D53,'Company Hitlist'!$A:$A,0)),) | O53: =IFERROR(INDEX('Company Hitlist'!$N:$N,MATCH(D53,'Company Hitlist'!$A:$A,0)),) | Q53: todo
A54: Bob Stewart | B54: Speaker | C54: Former SVP & Chief Supply Chain Officer NA | D54: McDonald's | H54: 29 | I54: TRUE | J54: TRUE | K54: TRUE | L54: FALSE | M54: FALSE | N54: =IFERROR(INDEX('Company Hitlist'!$AA:$AA,MATCH(D54,'Company Hitlist'!$A:$A,0)),) | O54: =IFERROR(INDEX('Company Hitlist'!$N:$N,MATCH(D54,'Company Hitlist'!$A:$A,0)),) | Q54: todo
A55: Dov Shenkman | B55: Speaker | C55: Former VP of Global Supply Chain | D55: Medtronic | H55: 29 | I55: TRUE | J55: TRUE | K55: TRUE | L55: FALSE | M55: FALSE | N55: =IFERROR(INDEX('Company Hitlist'!$AA:$AA,MATCH(D55,'Company Hitlist'!$A:$A,0)),) | O55: =IFERROR(INDEX('Company Hitlist'!$N:$N,MATCH(D55,'Company Hitlist'!$A:$A,0)),) | Q55: todo
A56: Jeff Davidson | B56: Speaker | C56: General Manager, Global Devices Customer Supply Chain | D56: Microsoft | H56: 29 | I56: TRUE | J56: TRUE | K56: TRUE | L56: FALSE | M56: FALSE | N56: =IFERROR(INDEX('Company Hitlist'!$AA:$AA,MATCH(D56,'Company Hitlist'!$A:$A,0)),) | O56: =IFERROR(INDEX('Company Hitlist'!$N:$N,MATCH(D56,'Company Hitlist'!$A:$A,0)),) | Q56: todo
A57: Neil Neufeld | B57: Speaker | C57: Chief Supply Chain Officer | D57: Misfits Market | H57: 29 | I57: TRUE | J57: TRUE | K57: TRUE | L57: FALSE | M57: FALSE | N57: =IFERROR(INDEX('Company Hitlist'!$AA:$AA,MATCH(D57,'Company Hitlist'!$A:$A,0)),) | O57: =IFERROR(INDEX('Company Hitlist'!$N:$N,MATCH(D57,'Company Hitlist'!$A:$A,0)),) | Q57: todo
A58: Agustin Harriague | B58: Speaker | C58: VP, Logistics & Supply Chain Operational Excellence | D58: Mitsubishi Power Americas | H58: 29 | I58: TRUE | J58: TRUE | K58: TRUE | L58: FALSE | M58: FALSE | N58: =IFERROR(INDEX('Company Hitlist'!$AA:$AA,MATCH(D58,'Company Hitlist'!$A:$A,0)),) | O58: =IFERROR(INDEX('Company Hitlist'!$N:$N,MATCH(D58,'Company Hitlist'!$A:$A,0)),) | Q58: todo
A59: Manju Parkhe | B59: Speaker | C59: EVP, Supply Chain | D59: Molex | H59: 29 | I59: TRUE | J59: TRUE | K59: TRUE | L59: FALSE | M59: FALSE | N59: =IFERROR(INDEX('Company Hitlist'!$AA:$AA,MATCH(D59,'Company Hitlist'!$A:$A,0)),) | O59: =IFERROR(INDEX('Company Hitlist'!$N:$N,MATCH(D59,'Company Hitlist'!$A:$A,0)),) | Q59: todo
A60: Keith Peterson | B60: Speaker | C60: VP Operations | D60: NMFTA | H60: 29 | I60: TRUE | J60: TRUE | K60: TRUE | L60: FALSE | M60: FALSE | N60: =IFERROR(INDEX('Company Hitlist'!$AA:$AA,MATCH(D60,'Company Hitlist'!$A:$A,0)),) | O60: =IFERROR(INDEX('Company Hitlist'!$N:$N,MATCH(D60,'Company Hitlist'!$A:$A,0)),) | Q60: todo
A61: Linda Reddy | B61: Speaker | C61: Global Head of Supply Chain | D61: Nando's Group Limited | H61: 29 | I61: TRUE | J61: TRUE | K61: TRUE | L61: FALSE | M61: FALSE | N61: =IFERROR(INDEX('Company Hitlist'!$AA:$AA,MATCH(D61,'Company Hitlist'!$A:$A,0)),) | O61: =IFERROR(INDEX('Company Hitlist'!$N:$N,MATCH(D61,'Company Hitlist'!$A:$A,0)),) | Q61: todo
A62: Michael Hopkins | B62: Speaker | C62: VP, Supply Chain Distribution & Logistics | D62: Northwestern Medicine | H62: 29 | I62: TRUE | J62: TRUE | K62: TRUE | L62: FALSE | M62: FALSE | N62: =IFERROR(INDEX('Company Hitlist'!$AA:$AA,MATCH(D62,'Company Hitlist'!$A:$A,0)),) | O62: =IFERROR(INDEX('Company Hitlist'!$N:$N,MATCH(D62,'Company Hitlist'!$A:$A,0)),) | Q62: todo
A63: Derek Geiss | B63: Speaker | C63: Chief Supply Chain Officer | D63: Nutrabolt | H63: 29 | I63: TRUE | J63: TRUE | K63: TRUE | L63: FALSE | M63: FALSE | N63: =IFERROR(INDEX('Company Hitlist'!$AA:$AA,MATCH(D63,'Company Hitlist'!$A:$A,0)),) | O63: =IFERROR(INDEX('Company Hitlist'!$N:$N,MATCH(D63,'Company Hitlist'!$A:$A,0)),) | Q63: todo
A64: Dawn Swackhamer | B64: Speaker | C64: VP Global Operations & Planning Technology | D64: Pandora | F64: Yes | G64: $4.76B (2025 est.) | H64: 29 | I64: TRUE | J64: TRUE | K64: TRUE | L64: FALSE | M64: FALSE | N64: =IFERROR(INDEX('Company Hitlist'!$AA:$AA,MATCH(D64,'Company Hitlist'!$A:$A,0)),) | O64: =IFERROR(INDEX('Company Hitlist'!$N:$N,MATCH(D64,'Company Hitlist'!$A:$A,0)),) | Q64: todo
A65: Audreyanne Snow | B65: Speaker | C65: VP, Operations & Logistics | D65: Parts Town | F65: Yes | G65: $2.5B (2024; projected similar in 2025) | H65: 29 | I65: TRUE | J65: TRUE | K65: TRUE | L65: FALSE | M65: FALSE | N65: =IFERROR(INDEX('Company Hitlist'!$AA:$AA,MATCH(D65,'Company Hitlist'!$A:$A,0)),) | O65: =IFERROR(INDEX('Company Hitlist'!$N:$N,MATCH(D65,'Company Hitlist'!$A:$A,0)),) | Q65: todo
A66: Lisa Backlin | B66: Speaker | C66: Group Senior Vice President, Supply Chain | D66: Parts Town | H66: 29 | I66: TRUE | J66: TRUE | K66: TRUE | L66: FALSE | M66: FALSE | N66: =IFERROR(INDEX('Company Hitlist'!$AA:$AA,MATCH(D66,'Company Hitlist'!$A:$A,0)),) | O66: =IFERROR(INDEX('Company Hitlist'!$N:$N,MATCH(D66,'Company Hitlist'!$A:$A,0)),) | Q66: todo
A67: Birger Buesching | B67: Speaker | C67: Head of Supply Chain North America, Personal Health | D67: Philips | H67: 29 | I67: TRUE | J67: TRUE | K67: TRUE | L67: FALSE | M67: FALSE | N67: =IFERROR(INDEX('Company Hitlist'!$AA:$AA,MATCH(D67,'Company Hitlist'!$A:$A,0)),) | O67: =IFERROR(INDEX('Company Hitlist'!$N:$N,MATCH(D67,'Company Hitlist'!$A:$A,0)),) | Q67: todo
A68: Matt Reddington | B68: Speaker | C68: Vice President Packaging + Logistics | D68: Procure Analytics | H68: 29 | I68: TRUE | J68: TRUE | K68: TRUE | L68: FALSE | M68: FALSE | N68: =IFERROR(INDEX('Company Hitlist'!$AA:$AA,MATCH(D68,'Company Hitlist'!$A:$A,0)),) | O68: =IFERROR(INDEX('Company Hitlist'!$N:$N,MATCH(D68,'Company Hitlist'!$A:$A,0)),) | Q68: todo
A69: Karon Evanoff | B69: Speaker | C69: SVP Global Operations | D69: QSC | F69: Yes | G69: $535M (2025 est.) (ICP match) | H69: 29 | I69: TRUE | J69: TRUE | K69: TRUE | L69: FALSE | M69: FALSE | N69: =IFERROR(INDEX('Company Hitlist'!$AA:$AA,MATCH(D69,'Company Hitlist'!$A:$A,0)),) | O69: =IFERROR(INDEX('Company Hitlist'!$N:$N,MATCH(D69,'Company Hitlist'!$A:$A,0)),) | Q69: todo
A70: Heather Burke | B70: Speaker | C70: SVP Logistics & Customer Experience | D70: Revolve | F70: Yes | G70: $1.19B (2025 est.) | H70: 29 | I70: TRUE | J70: TRUE | K70: TRUE | L70: FALSE | M70: FALSE | N70: =IFERROR(INDEX('Company Hitlist'!$AA:$AA,MATCH(D70,'Company Hitlist'!$A:$A,0)),) | O70: =IFERROR(INDEX('Company Hitlist'!$N:$N,MATCH(D70,'Company Hitlist'!$A:$A,0)),) | Q70: todo
A71: Scott Schienvar | B71: Speaker | C71: Chief Supply Chain Officer | D71: Sol de Janeiro | H71: 29 | I71: TRUE | J71: TRUE | K71: TRUE | L71: FALSE | M71: FALSE | N71: =IFERROR(INDEX('Company Hitlist'!$AA:$AA,MATCH(D71,'Company Hitlist'!$A:$A,0)),) | O71: =IFERROR(INDEX('Company Hitlist'!$N:$N,MATCH(D71,'Company Hitlist'!$A:$A,0)),) | Q71: todo
A72: Amanda Chawla | B72: Speaker | C72: SVP, Chief Supply Chain & Post Acute Care Officer | D72: Stanford Medicine | H72: 29 | I72: TRUE | J72: TRUE | K72: TRUE | L72: FALSE | M72: FALSE | N72: =IFERROR(INDEX('Company Hitlist'!$AA:$AA,MATCH(D72,'Company Hitlist'!$A:$A,0)),) | O72: =IFERROR(INDEX('Company Hitlist'!$N:$N,MATCH(D72,'Company Hitlist'!$A:$A,0)),) | Q72: todo
A73: Nilesh Mohan | B73: Speaker | C73: Vice President, Supply Chain Technology | D73: Staples | H73: 29 | I73: TRUE | J73: TRUE | K73: TRUE | L73: FALSE | M73: FALSE | N73: =IFERROR(INDEX('Company Hitlist'!$AA:$AA,MATCH(D73,'Company Hitlist'!$A:$A,0)),) | O73: =IFERROR(INDEX('Company Hitlist'!$N:$N,MATCH(D73,'Company Hitlist'!$A:$A,0)),) | Q73: todo
A74: Vickram Srivastava | B74: Speaker | C74: Head of Supply Chain - North America | D74: Sun Pharma | H74: 29 | I74: TRUE | J74: TRUE | K74: TRUE | L74: FALSE | M74: FALSE | N74: =IFERROR(INDEX('Company Hitlist'!$AA:$AA,MATCH(D74,'Company Hitlist'!$A:$A,0)),) | O74: =IFERROR(INDEX('Company Hitlist'!$N:$N,MATCH(D74,'Company Hitlist'!$A:$A,0)),) | Q74: todo
A75: Jamie Bragg | B75: Speaker | C75: EVP, Chief Supply Chain Officer | D75: Tailored Brands | H75: 29 | I75: TRUE | J75: TRUE | K75: TRUE | L75: FALSE | M75: FALSE | N75: =IFERROR(INDEX('Company Hitlist'!$AA:$AA,MATCH(D75,'Company Hitlist'!$A:$A,0)),) | O75: =IFERROR(INDEX('Company Hitlist'!$N:$N,MATCH(D75,'Company Hitlist'!$A:$A,0)),) | Q75: todo
A76: Daryl Glass | B76: Speaker | C76: SVP, Fulfillment & Last Mile | D76: Target | F76: Yes | G76: $106.57B (2025 est.) | H76: 29 | I76: TRUE | J76: TRUE | K76: TRUE | L76: FALSE | M76: FALSE | N76: =IFERROR(INDEX('Company Hitlist'!$AA:$AA,MATCH(D76,'Company Hitlist'!$A:$A,0)),) | O76: =IFERROR(INDEX('Company Hitlist'!$N:$N,MATCH(D76,'Company Hitlist'!$A:$A,0)),) | Q76: todo
A77: Pascal Montilus | B77: Speaker | C77: Chief Supply Chain Officer | D77: The Clorox Company | H77: 29 | I77: TRUE | J77: TRUE | K77: TRUE | L77: FALSE | M77: FALSE | N77: =IFERROR(INDEX('Company Hitlist'!$AA:$AA,MATCH(D77,'Company Hitlist'!$A:$A,0)),) | O77: =IFERROR(INDEX('Company Hitlist'!$N:$N,MATCH(D77,'Company Hitlist'!$A:$A,0)),) | Q77: todo
A78: Nish Embry | B78: Speaker | C78: Head of SCPMCOE Innovation & Supply Chain | D78: The Coca-Cola Company | H78: 29 | I78: TRUE | J78: TRUE | K78: TRUE | L78: FALSE | M78: FALSE | N78: =IFERROR(INDEX('Company Hitlist'!$AA:$AA,MATCH(D78,'Company Hitlist'!$A:$A,0)),) | O78: =IFERROR(INDEX('Company Hitlist'!$N:$N,MATCH(D78,'Company Hitlist'!$A:$A,0)),) | Q78: todo
A79: Florent Guillet | B79: Speaker | C79: VP Global Supply Chain Strategy & Value Acceleration | D79: The Estée Lauder Companies | H79: 29 | I79: TRUE | J79: TRUE | K79: TRUE | L79: FALSE | M79: FALSE | N79: =IFERROR(INDEX('Company Hitlist'!$AA:$AA,MATCH(D79,'Company Hitlist'!$A:$A,0)),) | O79: =IFERROR(INDEX('Company Hitlist'!$N:$N,MATCH(D79,'Company Hitlist'!$A:$A,0)),) | Q79: todo
A80: Dirk Martin | B80: Speaker | C80: Vice President of Global Logistics | D80: Trident Seafoods | H80: 29 | I80: TRUE | J80: TRUE | K80: TRUE | L80: FALSE | M80: FALSE | N80: =IFERROR(INDEX('Company Hitlist'!$AA:$AA,MATCH(D80,'Company Hitlist'!$A:$A,0)),) | O80: =IFERROR(INDEX('Company Hitlist'!$N:$N,MATCH(D80,'Company Hitlist'!$A:$A,0)),) | Q80: todo
A81: Angelo Ventrone | B81: Speaker | C81: VP of Logistics | D81: ULINE | F81: Yes | G81: 11000000000 | H81: 29 | I81: TRUE | J81: TRUE | K81: TRUE | L81: FALSE | M81: FALSE | N81: =IFERROR(INDEX('Company Hitlist'!$AA:$AA,MATCH(D81,'Company Hitlist'!$A:$A,0)),) | O81: =IFERROR(INDEX('Company Hitlist'!$N:$N,MATCH(D81,'Company Hitlist'!$A:$A,0)),) | Q81: todo
A82: Todd Jensen | B82: Speaker | C82: Chief of Operations | D82: USTRANSCOM | H82: 29 | I82: TRUE | J82: TRUE | K82: TRUE | L82: FALSE | M82: FALSE | N82: =IFERROR(INDEX('Company Hitlist'!$AA:$AA,MATCH(D82,'Company Hitlist'!$A:$A,0)),) | O82: =IFERROR(INDEX('Company Hitlist'!$N:$N,MATCH(D82,'Company Hitlist'!$A:$A,0)),) | Q82: todo
A83: Oronzo Suma | B83: Speaker | C83: Chief Supply Chain Performance Management Officer | D83: United Nations | H83: 29 | I83: TRUE | J83: TRUE | K83: TRUE | L83: FALSE | M83: FALSE | N83: =IFERROR(INDEX('Company Hitlist'!$AA:$AA,MATCH(D83,'Company Hitlist'!$A:$A,0)),) | O83: =IFERROR(INDEX('Company Hitlist'!$N:$N,MATCH(D83,'Company Hitlist'!$A:$A,0)),) | Q83: todo
A84: Anders Karlborg | B84: Speaker | C84: EVP, Manufacturing, Logistics & Operational Excellence | D84: Vertiv | F84: Yes | G84: $9.7B (2025 est.) | H84: 29 | I84: TRUE | J84: TRUE | K84: TRUE | L84: FALSE | M84: FALSE | N84: =IFERROR(INDEX('Company Hitlist'!$AA:$AA,MATCH(D84,'Company Hitlist'!$A:$A,0)),) | O84: =IFERROR(INDEX('Company Hitlist'!$N:$N,MATCH(D84,'Company Hitlist'!$A:$A,0)),) | Q84: todo
A85: Brendan Duttry | B85: Speaker | C85: VP Operations | D85: Wildgrain | F85: Yes | H85: 29 | I85: TRUE | J85: TRUE | K85: TRUE | L85: FALSE | M85: FALSE | N85: =IFERROR(INDEX('Company Hitlist'!$AA:$AA,MATCH(D85,'Company Hitlist'!$A:$A,0)),) | O85: =IFERROR(INDEX('Company Hitlist'!$N:$N,MATCH(D85,'Company Hitlist'!$A:$A,0)),) | Q85: todo
A86: Saxon McBride | B86: Speaker | C86: Vice President of Operations | D86: Zero Down Supply Chain Solutions | F86: Yes | G86: 54436000 | H86: 29 | I86: TRUE | J86: TRUE | K86: TRUE | L86: FALSE | M86: FALSE | N86: =IFERROR(INDEX('Company Hitlist'!$AA:$AA,MATCH(D86,'Company Hitlist'!$A:$A,0)),) | O86: =IFERROR(INDEX('Company Hitlist'!$N:$N,MATCH(D86,'Company Hitlist'!$A:$A,0)),) | Q86: todo
A87: Roger Sechler | B87: Sponsor | C87: Vice President of Transportation | D87: 4flow | F87: Yes | G87: 423000000 | H87: 28 | I87: TRUE | J87: TRUE | K87: TRUE | L87: FALSE | M87: FALSE | N87: =IFERROR(INDEX('Company Hitlist'!$AA:$AA,MATCH(D87,'Company Hitlist'!$A:$A,0)),) | O87: =IFERROR(INDEX('Company Hitlist'!$N:$N,MATCH(D87,'Company Hitlist'!$A:$A,0)),) | Q87: todo
A88: Doug King | B88: Sponsor | C88: VP of Transportation | D88: Cart.com | E88: United States | F88: Yes | H88: 28 | I88: TRUE | J88: TRUE | K88: TRUE | L88: FALSE | M88: FALSE | N88: =IFERROR(INDEX('Company Hitlist'!$AA:$AA,MATCH(D88,'Company Hitlist'!$A:$A,0)),) | O88: =IFERROR(INDEX('Company Hitlist'!$N:$N,MATCH(D88,'Company Hitlist'!$A:$A,0)),) | Q88: todo
A89: Mario Rivera | B89: Sponsor | C89: SVP, Fulfillment Solutions | D89: Cart.com | E89: United States | F89: Yes | H89: 28 | I89: TRUE | J89: TRUE | K89: TRUE | L89: FALSE | M89: FALSE | N89: =IFERROR(INDEX('Company Hitlist'!$AA:$AA,MATCH(D89,'Company Hitlist'!$A:$A,0)),) | O89: =IFERROR(INDEX('Company Hitlist'!$N:$N,MATCH(D89,'Company Hitlist'!$A:$A,0)),) | Q89: todo
A90: Alan Alberto | B90: Sponsor | C90: VP of Operations | D90: Cloneops.ai | E90: United States | F90: Yes | H90: 28 | I90: TRUE | J90: TRUE | K90: TRUE | L90: FALSE | M90: FALSE | N90: =IFERROR(INDEX('Company Hitlist'!$AA:$AA,MATCH(D90,'Company Hitlist'!$A:$A,0)),) | O90: =IFERROR(INDEX('Company Hitlist'!$N:$N,MATCH(D90,'Company Hitlist'!$A:$A,0)),) | Q90: todo
A91: James Hoskins | B91: Sponsor | C91: Vice President Operations | D91: DHL Supply Chain | E91: United States | F91: Yes | G91: $80B (2024; projected $82B in 2025) | H91: 28 | I91: TRUE | J91: TRUE | K91: TRUE | L91: FALSE | M91: FALSE | N91: =IFERROR(INDEX('Company Hitlist'!$AA:$AA,MATCH(D91,'Company Hitlist'!$A:$A,0)),) | O91: =IFERROR(INDEX('Company Hitlist'!$N:$N,MATCH(D91,'Company Hitlist'!$A:$A,0)),) | Q91: todo
A92: Todd Benton | B92: Sponsor | C92: Vice President Operations | D92: DHL Supply Chain | E92: United States | F92: Yes | G92: $80B (2024; projected $82B in 2025) | H92: 28 | I92: TRUE | J92: TRUE | K92: TRUE | L92: FALSE | M92: FALSE | N92: =IFERROR(INDEX('Company Hitlist'!$AA:$AA,MATCH(D92,'Company Hitlist'!$A:$A,0)),) | O92: =IFERROR(INDEX('Company Hitlist'!$N:$N,MATCH(D92,'Company Hitlist'!$A:$A,0)),) | Q92: todo
A93: Jake Armstrong | B93: Sponsor | C93: Vice President Operations | D93: DHL Supply Chain | F93: Yes | G93: $80B (2024; projected $82B in 2025) | H93: 28 | I93: TRUE | J93: TRUE | K93: TRUE | L93: FALSE | M93: FALSE | N93: =IFERROR(INDEX('Company Hitlist'!$AA:$AA,MATCH(D93,'Company Hitlist'!$A:$A,0)),) | O93: =IFERROR(INDEX('Company Hitlist'!$N:$N,MATCH(D93,'Company Hitlist'!$A:$A,0)),) | Q93: todo
A94: Paige Vanfossen | B94: Sponsor | C94: Vice President, Operations | D94: DHL Supply Chain | F94: Yes | G94: $80B (2024; projected $82B in 2025) | H94: 28 | I94: TRUE | J94: TRUE | K94: TRUE | L94: FALSE | M94: FALSE | N94: =IFERROR(INDEX('Company Hitlist'!$AA:$AA,MATCH(D94,'Company Hitlist'!$A:$A,0)),) | O94: =IFERROR(INDEX('Company Hitlist'!$N:$N,MATCH(D94,'Company Hitlist'!$A:$A,0)),) | Q94: todo
A95: Shaun Nakhost | B95: Sponsor | C95: VP Warehouse Operations | D95: Dependable Supply Chain Services | E95: United States | F95: Yes | G95: $522.5 million (2025) | H95: 28 | I95: TRUE | J95: TRUE | K95: TRUE | L95: FALSE | M95: FALSE | N95: =IFERROR(INDEX('Company Hitlist'!$AA:$AA,MATCH(D95,'Company Hitlist'!$A:$A,0)),) | O95: =IFERROR(INDEX('Company Hitlist'!$N:$N,MATCH(D95,'Company Hitlist'!$A:$A,0)),) | Q95: todo
A96: Phillip Agans | B96: Sponsor | C96: VP of Warehouse & Distribution Solutions | D96: Fives Intralogistics Corp. | E96: United States | F96: Yes | G96: $2.6B (est.) | H96: 28 | I96: TRUE | J96: TRUE | K96: TRUE | L96: FALSE | M96: FALSE | N96: =IFERROR(INDEX('Company Hitlist'!$AA:$AA,MATCH(D96,'Company Hitlist'!$A:$A,0)),) | O96: =IFERROR(INDEX('Company Hitlist'!$N:$N,MATCH(D96,'Company Hitlist'!$A:$A,0)),) | Q96: todo
A97: Sebastian Wouters | B97: Sponsor | C97: VP Network Operations | D97: FlavorCloud | E97: United States | F97: Yes | G97: 12000000 | H97: 28 | I97: TRUE | J97: TRUE | K97: TRUE | L97: FALSE | M97: FALSE | N97: =IFERROR(INDEX('Company Hitlist'!$AA:$AA,MATCH(D97,'Company Hitlist'!$A:$A,0)),) | O97: =IFERROR(INDEX('Company Hitlist'!$N:$N,MATCH(D97,'Company Hitlist'!$A:$A,0)),) | Q97: todo
A98: Mike Castle | B98: Sponsor | C98: Head of Transportation and Parcel Strategy | D98: Flexport | E98: United States | F98: Yes | G98: $3 billion (2025) | H98: 28 | I98: TRUE | J98: TRUE | K98: TRUE | L98: FALSE | M98: FALSE | N98: =IFERROR(INDEX('Company Hitlist'!$AA:$AA,MATCH(D98,'Company Hitlist'!$A:$A,0)),) | O98: =IFERROR(INDEX('Company Hitlist'!$N:$N,MATCH(D98,'Company Hitlist'!$A:$A,0)),) | Q98: todo
A99: John Lower | B99: Sponsor | C99: VP, Transportation Brokerage | D99: GEODIS | E99: United States | F99: Yes | G99: 12114000000 | H99: 28 | I99: TRUE | J99: TRUE | K99: TRUE | L99: FALSE | M99: FALSE | N99: =IFERROR(INDEX('Company Hitlist'!$AA:$AA,MATCH(D99,'Company Hitlist'!$A:$A,0)),) | O99: =IFERROR(INDEX('Company Hitlist'!$N:$N,MATCH(D99,'Company Hitlist'!$A:$A,0)),) | Q99: todo
A100: Sean Mitchell | B100: Sponsor | C100: VP of Customer Operations | D100: Gather AI | E100: United States | F100: Yes | H100: 28 | I100: TRUE | J100: TRUE | K100: TRUE | L100: FALSE | M100: FALSE | N100: =IFERROR(INDEX('Company Hitlist'!$AA:$AA,MATCH(D100,'Company Hitlist'!$A:$A,0)),) | O100: =IFERROR(INDEX('Company Hitlist'!$N:$N,MATCH(D100,'Company Hitlist'!$A:$A,0)),) | Q100: todo
...
